{"converged": [1], "align_changechi2": [0.61668], "align_totaldeltachi2": [6851.2890625], "align_error2": [0.0225577], "Tx_chi2": [782.156], "Ty_chi2": [749.674], "Tz_chi2": [716.553], "Rx_chi2": [771.595], "Ry_chi2": [869.776], "Rz_chi2": [784.434], "FT/T1/U/HL0/Q0/M0": {"Tx": ["-0.07328,"], "Ty": ["0.0002868,"], "Tz": ["0.1353,"], "Rx": ["-0.0008697,"], "Ry": ["-1.017e-07,"], "Rz": ["4.003e-05"], "x_global": ["-371.71"], "y_global": ["-1208.25"], "z_global": ["7891.55"], "average_hit_x": ["-303.55"], "average_hit_y": ["-354.3"], "average_hit_z": ["7896.31"], "nTracks": ["528977"], "nHits": ["528977"], "localDeltaChi2": [769.0]}, "FT/T1/U/HL0/Q0/M1": {"Tx": ["-0.09612,"], "Ty": ["8.707e-05,"], "Tz": ["0.1862,"], "Rx": ["0.0003016,"], "Ry": ["2.277e-07,"], "Rz": ["6.717e-06"], "x_global": ["-903.7"], "y_global": ["-1208"], "z_global": ["7892"], "average_hit_x": ["-802.3"], "average_hit_y": ["-425.8"], "average_hit_z": ["7895"], "nTracks": ["555607"], "nHits": ["555607"], "localDeltaChi2": [2367.0]}, "FT/T1/U/HL0/Q0/M2": {"Tx": ["0.1072,"], "Ty": ["0.0002927,"], "Tz": ["0.8269,"], "Rx": ["-8.79e-05,"], "Ry": ["2.515e-07,"], "Rz": ["-0.0001194"], "x_global": ["-1436"], "y_global": ["-1208"], "z_global": ["7892"], "average_hit_x": ["-1312"], "average_hit_y": ["-546.9"], "average_hit_z": ["7896"], "nTracks": ["172890"], "nHits": ["172890"], "localDeltaChi2": [3272.0]}, "FT/T1/U/HL0/Q0/M3": {"Tx": ["-0.112,"], "Ty": ["-4.605e-05,"], "Tz": ["0.01791,"], "Rx": ["9.143e-05,"], "Ry": ["1.349e-07,"], "Rz": ["-2.981e-05"], "x_global": ["-1968"], "y_global": ["-1208"], "z_global": ["7892"], "average_hit_x": ["-1894"], "average_hit_y": ["-644.3"], "average_hit_z": ["7896"], "nTracks": ["55708"], "nHits": ["55708"], "localDeltaChi2": [2149.0]}, "FT/T1/U/HL0/Q0/M4": {"Tx": ["-0.1837,"], "Ty": ["0.0004444,"], "Tz": ["0.228,"], "Rx": ["-0.0002653,"], "Ry": ["1.541e-08,"], "Rz": ["0.0001655"], "x_global": ["-2500"], "y_global": ["-1208"], "z_global": ["7892"], "average_hit_x": ["-2237"], "average_hit_y": ["-422.7"], "average_hit_z": ["7896"], "nTracks": ["6723"], "nHits": ["6723"], "localDeltaChi2": [2948.0]}, "FT/T1/U/HL0/Q2/M0": {"Tx": ["0.4102,"], "Ty": ["3.877e-05,"], "Tz": ["0.8225,"], "Rx": ["-0.0003031,"], "Ry": ["6.951e-07,"], "Rz": ["-0.0003179"], "x_global": ["-160.3"], "y_global": ["1208"], "z_global": ["7900"], "average_hit_x": ["-143.1"], "average_hit_y": ["367.1"], "average_hit_z": ["7896"], "nTracks": ["239360"], "nHits": ["239360"], "localDeltaChi2": [771.0]}, "FT/T1/U/HL0/Q2/M1": {"Tx": ["0.9415,"], "Ty": ["7.682e-05,"], "Tz": ["0.2363,"], "Rx": ["0.0003448,"], "Ry": ["2.982e-07,"], "Rz": ["-0.0007038"], "x_global": ["-692.3"], "y_global": ["1208"], "z_global": ["7900"], "average_hit_x": ["-771.5"], "average_hit_y": ["148.6"], "average_hit_z": ["7896"], "nTracks": ["169840"], "nHits": ["169840"], "localDeltaChi2": [2365.0]}, "FT/T1/U/HL0/Q2/M2": {"Tx": ["0.6935,"], "Ty": ["0.000389,"], "Tz": ["1.122,"], "Rx": ["0.0001513,"], "Ry": ["3.647e-07,"], "Rz": ["-0.0005408"], "x_global": ["-1224"], "y_global": ["1208"], "z_global": ["7900"], "average_hit_x": ["-1258"], "average_hit_y": ["218.6"], "average_hit_z": ["7897"], "nTracks": ["85001"], "nHits": ["85001"], "localDeltaChi2": [3271.0]}, "FT/T1/U/HL0/Q2/M3": {"Tx": ["0.9086,"], "Ty": ["0.0004792,"], "Tz": ["0.3585,"], "Rx": ["0.0003706,"], "Ry": ["4.44e-07,"], "Rz": ["-0.0006271"], "x_global": ["-1756"], "y_global": ["1208"], "z_global": ["7900"], "average_hit_x": ["-1782"], "average_hit_y": ["348.1"], "average_hit_z": ["7896"], "nTracks": ["26595"], "nHits": ["26595"], "localDeltaChi2": [2149.0]}, "FT/T1/U/HL0/Q2/M4": {"Tx": ["-0.2003,"], "Ty": ["0.0005866,"], "Tz": ["0.8204,"], "Rx": ["0.0002229,"], "Ry": ["9.357e-08,"], "Rz": ["0.0001512"], "x_global": ["-2288"], "y_global": ["1208"], "z_global": ["7900"], "average_hit_x": ["-2187"], "average_hit_y": ["426.8"], "average_hit_z": ["7897"], "nTracks": ["5635"], "nHits": ["5635"], "localDeltaChi2": [2948.0]}, "FT/T1/U/HL1/Q1/M0": {"Tx": ["-0.08644,"], "Ty": ["-0.0003719,"], "Tz": ["0.6399,"], "Rx": ["0.0001248,"], "Ry": ["-1.615e-07,"], "Rz": ["-2.7e-05"], "x_global": ["160.3"], "y_global": ["-1208"], "z_global": ["7892"], "average_hit_x": ["190.1"], "average_hit_y": ["-349.2"], "average_hit_z": ["7896"], "nTracks": ["449121"], "nHits": ["449121"], "localDeltaChi2": [1137.5]}, "FT/T1/U/HL1/Q1/M1": {"Tx": ["-0.2072,"], "Ty": ["6.24e-05,"], "Tz": ["1.385,"], "Rx": ["-3.541e-05,"], "Ry": ["5.986e-08,"], "Rz": ["-0.0001129"], "x_global": ["692.3"], "y_global": ["-1208"], "z_global": ["7892"], "average_hit_x": ["766.8"], "average_hit_y": ["-158.7"], "average_hit_z": ["7897"], "nTracks": ["186630"], "nHits": ["186630"], "localDeltaChi2": [244.35]}, "FT/T1/U/HL1/Q1/M2": {"Tx": ["0.7758,"], "Ty": ["0.0003944,"], "Tz": ["0.6405,"], "Rx": ["-0.0005275,"], "Ry": ["8.64e-08,"], "Rz": ["-0.0009838"], "x_global": ["1224"], "y_global": ["-1208"], "z_global": ["7892"], "average_hit_x": ["1255"], "average_hit_y": ["-217.6"], "average_hit_z": ["7898"], "nTracks": ["83314"], "nHits": ["83314"], "localDeltaChi2": [63.5]}, "FT/T1/U/HL1/Q1/M3": {"Tx": ["0.382,"], "Ty": ["0.0002664,"], "Tz": ["0.4616,"], "Rx": ["-0.0004097,"], "Ry": ["9.515e-09,"], "Rz": ["-0.0007714"], "x_global": ["1756"], "y_global": ["-1208"], "z_global": ["7892"], "average_hit_x": ["1799"], "average_hit_y": ["-345.3"], "average_hit_z": ["7897"], "nTracks": ["34884"], "nHits": ["34884"], "localDeltaChi2": [611.0]}, "FT/T1/U/HL1/Q1/M4": {"Tx": ["0.872,"], "Ty": ["-0.002125,"], "Tz": ["-0.497,"], "Rx": ["-0.001394,"], "Ry": ["8.035e-07,"], "Rz": ["-0.000993"], "x_global": ["2288"], "y_global": ["-1208"], "z_global": ["7892"], "average_hit_x": ["2202"], "average_hit_y": ["-415.8"], "average_hit_z": ["7897"], "nTracks": ["8078"], "nHits": ["8078"], "localDeltaChi2": [555.5]}, "FT/T1/U/HL1/Q3/M0": {"Tx": ["0.4813,"], "Ty": ["-0.000385,"], "Tz": ["0.8875,"], "Rx": ["0.0003285,"], "Ry": ["-7.091e-08,"], "Rz": ["-0.0002986"], "x_global": ["371.7"], "y_global": ["1208"], "z_global": ["7900"], "average_hit_x": ["293.3"], "average_hit_y": ["358.5"], "average_hit_z": ["7896"], "nTracks": ["707314"], "nHits": ["707314"], "localDeltaChi2": [1146.0]}, "FT/T1/U/HL1/Q3/M1": {"Tx": ["0.4855,"], "Ty": ["-0.003094,"], "Tz": ["2.343,"], "Rx": ["0.0007505,"], "Ry": ["-2.09e-07,"], "Rz": ["-0.0001165"], "x_global": ["903.7"], "y_global": ["1208"], "z_global": ["7900"], "average_hit_x": ["797.2"], "average_hit_y": ["410.8"], "average_hit_z": ["7896"], "nTracks": ["471694"], "nHits": ["471694"], "localDeltaChi2": [250.5]}, "FT/T1/U/HL1/Q3/M2": {"Tx": ["0.6842,"], "Ty": ["-0.003717,"], "Tz": ["2.324,"], "Rx": ["0.0008659,"], "Ry": ["-4.127e-07,"], "Rz": ["-0.0002201"], "x_global": ["1436"], "y_global": ["1208"], "z_global": ["7900"], "average_hit_x": ["1327"], "average_hit_y": ["548.5"], "average_hit_z": ["7897"], "nTracks": ["186310"], "nHits": ["186310"], "localDeltaChi2": [67.85]}, "FT/T1/U/HL1/Q3/M3": {"Tx": ["0.9974,"], "Ty": ["-0.007233,"], "Tz": ["2.644,"], "Rx": ["0.001388,"], "Ry": ["4.973e-08,"], "Rz": ["-0.000366"], "x_global": ["1968"], "y_global": ["1208"], "z_global": ["7900"], "average_hit_x": ["1872"], "average_hit_y": ["624.1"], "average_hit_z": ["7896"], "nTracks": ["63895"], "nHits": ["63895"], "localDeltaChi2": [613.0]}, "FT/T1/U/HL1/Q3/M4": {"Tx": ["0.5971,"], "Ty": ["-0.004858,"], "Tz": ["2.482,"], "Rx": ["0.001063,"], "Ry": ["1.612e-08,"], "Rz": ["-0.0002184"], "x_global": ["2500"], "y_global": ["1208"], "z_global": ["7900"], "average_hit_x": ["2237"], "average_hit_y": ["442.1"], "average_hit_z": ["7897"], "nTracks": ["6645"], "nHits": ["6645"], "localDeltaChi2": [555.5]}, "FT/T1/V/HL0/Q0/M0": {"Tx": ["-0.4221,"], "Ty": ["-0.002482,"], "Tz": ["1.138,"], "Rx": ["0.0009143,"], "Ry": ["-6.631e-08,"], "Rz": ["-0.000216"], "x_global": ["-160.3"], "y_global": ["-1208"], "z_global": ["7962"], "average_hit_x": ["-227.3"], "average_hit_y": ["-364.9"], "average_hit_z": ["7965"], "nTracks": ["524755"], "nHits": ["524755"], "localDeltaChi2": [1032.0]}, "FT/T1/V/HL0/Q0/M1": {"Tx": ["-0.2378,"], "Ty": ["-0.001253,"], "Tz": ["0.9229,"], "Rx": ["-5.293e-06,"], "Ry": ["-1.56e-08,"], "Rz": ["8.562e-05"], "x_global": ["-692.3"], "y_global": ["-1208"], "z_global": ["7962"], "average_hit_x": ["-742.6"], "average_hit_y": ["-403.9"], "average_hit_z": ["7964"], "nTracks": ["570073"], "nHits": ["570073"], "localDeltaChi2": [1352.5]}, "FT/T1/V/HL0/Q0/M2": {"Tx": ["0.1824,"], "Ty": ["0.0004661,"], "Tz": ["1.345,"], "Rx": ["-0.000431,"], "Ry": ["1.804e-07,"], "Rz": ["-8.846e-05"], "x_global": ["-1224"], "y_global": ["-1208"], "z_global": ["7962"], "average_hit_x": ["-1224"], "average_hit_y": ["-581.1"], "average_hit_z": ["7964"], "nTracks": ["222892"], "nHits": ["222892"], "localDeltaChi2": [2913.0]}, "FT/T1/V/HL0/Q0/M3": {"Tx": ["-0.03656,"], "Ty": ["2.302e-05,"], "Tz": ["1.171,"], "Rx": ["-0.0003601,"], "Ry": ["2.828e-07,"], "Rz": ["3.38e-05"], "x_global": ["-1756"], "y_global": ["-1208"], "z_global": ["7962"], "average_hit_x": ["-1784"], "average_hit_y": ["-690.9"], "average_hit_z": ["7965"], "nTracks": ["64484"], "nHits": ["64484"], "localDeltaChi2": [2101.0]}, "FT/T1/V/HL0/Q0/M4": {"Tx": ["-0.6371,"], "Ty": ["-0.000837,"], "Tz": ["0.6336,"], "Rx": ["-0.0007696,"], "Ry": ["-1.715e-07,"], "Rz": ["0.0005129"], "x_global": ["-2288"], "y_global": ["-1208"], "z_global": ["7962"], "average_hit_x": ["-2183"], "average_hit_y": ["-699.8"], "average_hit_z": ["7965"], "nTracks": ["17885"], "nHits": ["17885"], "localDeltaChi2": [1914.0]}, "FT/T1/V/HL0/Q2/M0": {"Tx": ["0.6607,"], "Ty": ["-0.003073,"], "Tz": ["0.8382,"], "Rx": ["0.0006652,"], "Ry": ["1.732e-06,"], "Rz": ["1.929e-05"], "x_global": ["-371.7"], "y_global": ["1208"], "z_global": ["7970"], "average_hit_x": ["-159"], "average_hit_y": ["318.8"], "average_hit_z": ["7965"], "nTracks": ["173685"], "nHits": ["173685"], "localDeltaChi2": [1034.0]}, "FT/T1/V/HL0/Q2/M1": {"Tx": ["-0.2843,"], "Ty": ["-0.001692,"], "Tz": ["0.5346,"], "Rx": ["-0.0003234,"], "Ry": ["-6.493e-07,"], "Rz": ["0.0003449"], "x_global": ["-903.7"], "y_global": ["1208"], "z_global": ["7970"], "average_hit_x": ["-802.9"], "average_hit_y": ["155.1"], "average_hit_z": ["7964"], "nTracks": ["172082"], "nHits": ["172082"], "localDeltaChi2": [1352.0]}, "FT/T1/V/HL0/Q2/M2": {"Tx": ["-0.2973,"], "Ty": ["-0.0001374,"], "Tz": ["0.9938,"], "Rx": ["-0.0007238,"], "Ry": ["-8.341e-07,"], "Rz": ["0.0001832"], "x_global": ["-1436"], "y_global": ["1208"], "z_global": ["7970"], "average_hit_x": ["-1304"], "average_hit_y": ["226.9"], "average_hit_z": ["7964"], "nTracks": ["82627"], "nHits": ["82627"], "localDeltaChi2": [2912.5]}, "FT/T1/V/HL0/Q2/M3": {"Tx": ["0.5492,"], "Ty": ["0.001085,"], "Tz": ["0.8636,"], "Rx": ["-0.0006146,"], "Ry": ["-6.853e-07,"], "Rz": ["-0.0004565"], "x_global": ["-1968"], "y_global": ["1208"], "z_global": ["7970"], "average_hit_x": ["-1844"], "average_hit_y": ["342.2"], "average_hit_z": ["7964"], "nTracks": ["28125"], "nHits": ["28125"], "localDeltaChi2": [2101.0]}, "FT/T1/V/HL0/Q2/M4": {"Tx": ["0.4904,"], "Ty": ["-0.0005402,"], "Tz": ["2.039,"], "Rx": ["0.000389,"], "Ry": ["-1.104e-07,"], "Rz": ["-0.0003919"], "x_global": ["-2500"], "y_global": ["1208"], "z_global": ["7970"], "average_hit_x": ["-2403"], "average_hit_y": ["309"], "average_hit_z": ["7965"], "nTracks": ["53"], "nHits": ["53"], "localDeltaChi2": [1914.0]}, "FT/T1/V/HL1/Q1/M0": {"Tx": ["-0.05969,"], "Ty": ["-0.000653,"], "Tz": ["1.079,"], "Rx": ["0.0003037,"], "Ry": ["4.765e-07,"], "Rz": ["-0.0001054"], "x_global": ["371.7"], "y_global": ["-1208"], "z_global": ["7962"], "average_hit_x": ["242.3"], "average_hit_y": ["-293.5"], "average_hit_z": ["7965"], "nTracks": ["383308"], "nHits": ["383308"], "localDeltaChi2": [1051.0]}, "FT/T1/V/HL1/Q1/M1": {"Tx": ["0.1128,"], "Ty": ["0.00159,"], "Tz": ["1.409,"], "Rx": ["-0.0005643,"], "Ry": ["-7.321e-07,"], "Rz": ["-4.577e-06"], "x_global": ["903.7"], "y_global": ["-1208"], "z_global": ["7962"], "average_hit_x": ["797.7"], "average_hit_y": ["-162.6"], "average_hit_z": ["7964"], "nTracks": ["181709"], "nHits": ["181709"], "localDeltaChi2": [749.0]}, "FT/T1/V/HL1/Q1/M2": {"Tx": ["0.3288,"], "Ty": ["0.003069,"], "Tz": ["1.08,"], "Rx": ["-0.001151,"], "Ry": ["-1.541e-06,"], "Rz": ["0.0002137"], "x_global": ["1436"], "y_global": ["-1208"], "z_global": ["7962"], "average_hit_x": ["1301"], "average_hit_y": ["-228.2"], "average_hit_z": ["7963"], "nTracks": ["79227"], "nHits": ["79227"], "localDeltaChi2": [342.15]}, "FT/T1/V/HL1/Q1/M3": {"Tx": ["-0.4095,"], "Ty": ["0.001661,"], "Tz": ["0.9348,"], "Rx": ["-0.0005474,"], "Ry": ["-6.498e-07,"], "Rz": ["0.0007942"], "x_global": ["1968"], "y_global": ["-1208"], "z_global": ["7962"], "average_hit_x": ["1859"], "average_hit_y": ["-351.5"], "average_hit_z": ["7964"], "nTracks": ["33398"], "nHits": ["33398"], "localDeltaChi2": [408.55]}, "FT/T1/V/HL1/Q1/M4": {"Tx": ["-1.792,"], "Ty": ["-0.00466,"], "Tz": ["2.324,"], "Rx": ["0.0006008,"], "Ry": ["6.534e-07,"], "Rz": ["0.001496"], "x_global": ["2500"], "y_global": ["-1208"], "z_global": ["7962"], "average_hit_x": ["2254"], "average_hit_y": ["-369.9"], "average_hit_z": ["7965"], "nTracks": ["6093"], "nHits": ["6093"], "localDeltaChi2": [4201.5]}, "FT/T1/V/HL1/Q3/M0": {"Tx": ["-0.1602,"], "Ty": ["0.0004238,"], "Tz": ["0.3749,"], "Rx": ["-0.0002777,"], "Ry": ["-1.552e-07,"], "Rz": ["0.0002867"], "x_global": ["160.3"], "y_global": ["1208"], "z_global": ["7970"], "average_hit_x": ["245"], "average_hit_y": ["356.2"], "average_hit_z": ["7965"], "nTracks": ["671373"], "nHits": ["671373"], "localDeltaChi2": [1060.0]}, "FT/T1/V/HL1/Q3/M1": {"Tx": ["-0.3984,"], "Ty": ["0.001813,"], "Tz": ["0.798,"], "Rx": ["-0.001062,"], "Ry": ["-4.083e-07,"], "Rz": ["0.0002401"], "x_global": ["692.3"], "y_global": ["1208"], "z_global": ["7970"], "average_hit_x": ["730.8"], "average_hit_y": ["398.6"], "average_hit_z": ["7964"], "nTracks": ["496845"], "nHits": ["496845"], "localDeltaChi2": [756.0]}, "FT/T1/V/HL1/Q3/M2": {"Tx": ["-1.051,"], "Ty": ["0.001975,"], "Tz": ["0.7452,"], "Rx": ["-0.00143,"], "Ry": ["-4.779e-07,"], "Rz": ["0.0003822"], "x_global": ["1224"], "y_global": ["1208"], "z_global": ["7970"], "average_hit_x": ["1237"], "average_hit_y": ["548.6"], "average_hit_z": ["7963"], "nTracks": ["216508"], "nHits": ["216508"], "localDeltaChi2": [345.45]}, "FT/T1/V/HL1/Q3/M3": {"Tx": ["-0.945,"], "Ty": ["0.0007358,"], "Tz": ["0.3552,"], "Rx": ["-0.001025,"], "Ry": ["-1.088e-07,"], "Rz": ["0.0003226"], "x_global": ["1756"], "y_global": ["1208"], "z_global": ["7970"], "average_hit_x": ["1761"], "average_hit_y": ["691.3"], "average_hit_z": ["7964"], "nTracks": ["79780"], "nHits": ["79780"], "localDeltaChi2": [410.1]}, "FT/T1/V/HL1/Q3/M4": {"Tx": ["-0.7614,"], "Ty": ["-0.0004138,"], "Tz": ["-0.1388,"], "Rx": ["-0.00143,"], "Ry": ["2.418e-07,"], "Rz": ["0.0006095"], "x_global": ["2288"], "y_global": ["1208"], "z_global": ["7970"], "average_hit_x": ["2183"], "average_hit_y": ["727.4"], "average_hit_z": ["7965"], "nTracks": ["17908"], "nHits": ["17908"], "localDeltaChi2": [4201.5]}, "FT/T1/X1/HL0/Q0/M0": {"Tx": ["0.1061,"], "Ty": ["-0.0005445,"], "Tz": ["0.5216,"], "Rx": ["0.0006654,"], "Ry": ["4.278e-08,"], "Rz": ["-2.459e-05"], "x_global": ["-265"], "y_global": ["-1213"], "z_global": ["7822"], "average_hit_x": ["-265.8"], "average_hit_y": ["-348.2"], "average_hit_z": ["7825"], "nTracks": ["527669"], "nHits": ["527669"], "localDeltaChi2": [943.0]}, "FT/T1/X1/HL0/Q0/M1": {"Tx": ["-0.2296,"], "Ty": ["9.829e-05,"], "Tz": ["0.6035,"], "Rx": ["-0.0002601,"], "Ry": ["2.259e-07,"], "Rz": ["0.0001274"], "x_global": ["-795"], "y_global": ["-1213"], "z_global": ["7822"], "average_hit_x": ["-765.8"], "average_hit_y": ["-416.8"], "average_hit_z": ["7825"], "nTracks": ["566889"], "nHits": ["566889"], "localDeltaChi2": [1603.5]}, "FT/T1/X1/HL0/Q0/M2": {"Tx": ["-0.5649,"], "Ty": ["-0.0002905,"], "Tz": ["0.1067,"], "Rx": ["-0.0002934,"], "Ry": ["2.701e-07,"], "Rz": ["0.0002546"], "x_global": ["-1325"], "y_global": ["-1213"], "z_global": ["7822"], "average_hit_x": ["-1264"], "average_hit_y": ["-563.1"], "average_hit_z": ["7825"], "nTracks": ["186573"], "nHits": ["186573"], "localDeltaChi2": [2852.5]}, "FT/T1/X1/HL0/Q0/M3": {"Tx": ["-0.1934,"], "Ty": ["0.0004373,"], "Tz": ["0.6172,"], "Rx": ["-0.0002306,"], "Ry": ["1.757e-07,"], "Rz": ["0.0002323"], "x_global": ["-1855"], "y_global": ["-1213"], "z_global": ["7822"], "average_hit_x": ["-1844"], "average_hit_y": ["-697"], "average_hit_z": ["7825"], "nTracks": ["53629"], "nHits": ["53629"], "localDeltaChi2": [2045.0]}, "FT/T1/X1/HL0/Q0/M4": {"Tx": ["-0.6081,"], "Ty": ["0.0003387,"], "Tz": ["0.4933,"], "Rx": ["-0.0001679,"], "Ry": ["6.84e-08,"], "Rz": ["0.0002671"], "x_global": ["-2385"], "y_global": ["-1213"], "z_global": ["7822"], "average_hit_x": ["-2196"], "average_hit_y": ["-545.6"], "average_hit_z": ["7826"], "nTracks": ["8937"], "nHits": ["8937"], "localDeltaChi2": [2546.5]}, "FT/T1/X1/HL0/Q2/M0": {"Tx": ["-0.4683,"], "Ty": ["-0.001183,"], "Tz": ["0.3562,"], "Rx": ["0.0005255,"], "Ry": ["1.075e-06,"], "Rz": ["0.0003232"], "x_global": ["-265"], "y_global": ["1213"], "z_global": ["7830"], "average_hit_x": ["-164.3"], "average_hit_y": ["333.7"], "average_hit_z": ["7826"], "nTracks": ["200849"], "nHits": ["200849"], "localDeltaChi2": [945.0]}, "FT/T1/X1/HL0/Q2/M1": {"Tx": ["-1.967,"], "Ty": ["-0.001485,"], "Tz": ["0.4776,"], "Rx": ["-0.0003611,"], "Ry": ["-1.284e-07,"], "Rz": ["0.001684"], "x_global": ["-795"], "y_global": ["1213"], "z_global": ["7830"], "average_hit_x": ["-780.9"], "average_hit_y": ["147.4"], "average_hit_z": ["7825"], "nTracks": ["169647"], "nHits": ["169647"], "localDeltaChi2": [1602.5]}, "FT/T1/X1/HL0/Q2/M2": {"Tx": ["-0.2523,"], "Ty": ["-0.0001161,"], "Tz": ["0.02137,"], "Rx": ["-0.0003632,"], "Ry": ["-2.293e-07,"], "Rz": ["0.0004192"], "x_global": ["-1325"], "y_global": ["1213"], "z_global": ["7830"], "average_hit_x": ["-1277"], "average_hit_y": ["226.3"], "average_hit_z": ["7825"], "nTracks": ["80772"], "nHits": ["80772"], "localDeltaChi2": [2852.0]}, "FT/T1/X1/HL0/Q2/M3": {"Tx": ["0.4817,"], "Ty": ["0.0008313,"], "Tz": ["0.2053,"], "Rx": ["-0.0005704,"], "Ry": ["-1.426e-07,"], "Rz": ["-0.00047"], "x_global": ["-1855"], "y_global": ["1213"], "z_global": ["7830"], "average_hit_x": ["-1806"], "average_hit_y": ["341.5"], "average_hit_z": ["7825"], "nTracks": ["28031"], "nHits": ["28031"], "localDeltaChi2": [2045.0]}, "FT/T1/X1/HL0/Q2/M4": {"Tx": ["0.8503,"], "Ty": ["0.001118,"], "Tz": ["0.6139,"], "Rx": ["-6.835e-05,"], "Ry": ["-1.07e-07,"], "Rz": ["-0.0004669"], "x_global": ["-2385"], "y_global": ["1213"], "z_global": ["7830"], "average_hit_x": ["-2195"], "average_hit_y": ["393.6"], "average_hit_z": ["7826"], "nTracks": ["3671"], "nHits": ["3671"], "localDeltaChi2": [2546.5]}, "FT/T1/X1/HL1/Q1/M0": {"Tx": ["-0.3848,"], "Ty": ["-0.0003273,"], "Tz": ["-0.02994,"], "Rx": ["0.0001658,"], "Ry": ["1.032e-07,"], "Rz": ["0.0002885"], "x_global": ["265"], "y_global": ["-1213"], "z_global": ["7822"], "average_hit_x": ["214.4"], "average_hit_y": ["-313.9"], "average_hit_z": ["7826"], "nTracks": ["407549"], "nHits": ["407549"], "localDeltaChi2": [1047.5]}, "FT/T1/X1/HL1/Q1/M1": {"Tx": ["-0.3268,"], "Ty": ["-0.0007139,"], "Tz": ["-0.8387,"], "Rx": ["-0.0003658,"], "Ry": ["-5.983e-07,"], "Rz": ["0.0005391"], "x_global": ["795"], "y_global": ["-1213"], "z_global": ["7822"], "average_hit_x": ["776"], "average_hit_y": ["-156.5"], "average_hit_z": ["7826"], "nTracks": ["186684"], "nHits": ["186684"], "localDeltaChi2": [511.5]}, "FT/T1/X1/HL1/Q1/M2": {"Tx": ["-0.3438,"], "Ty": ["-7.77e-05,"], "Tz": ["-0.1513,"], "Rx": ["-4.195e-05,"], "Ry": ["-1.263e-07,"], "Rz": ["0.0004966"], "x_global": ["1325"], "y_global": ["-1213"], "z_global": ["7822"], "average_hit_x": ["1273"], "average_hit_y": ["-222.6"], "average_hit_z": ["7826"], "nTracks": ["78813"], "nHits": ["78813"], "localDeltaChi2": [382.4]}, "FT/T1/X1/HL1/Q1/M3": {"Tx": ["-0.7722,"], "Ty": ["-0.001073,"], "Tz": ["0.3646,"], "Rx": ["0.000477,"], "Ry": ["5.204e-07,"], "Rz": ["0.0008769"], "x_global": ["1855"], "y_global": ["-1213"], "z_global": ["7822"], "average_hit_x": ["1819"], "average_hit_y": ["-349.2"], "average_hit_z": ["7826"], "nTracks": ["34069"], "nHits": ["34069"], "localDeltaChi2": [463.1]}, "FT/T1/X1/HL1/Q1/M4": {"Tx": ["-1.153,"], "Ty": ["-0.006747,"], "Tz": ["1.593,"], "Rx": ["0.001664,"], "Ry": ["2.322e-06,"], "Rz": ["0.001305"], "x_global": ["2385"], "y_global": ["-1213"], "z_global": ["7822"], "average_hit_x": ["2206"], "average_hit_y": ["-373.7"], "average_hit_z": ["7827"], "nTracks": ["5420"], "nHits": ["5420"], "localDeltaChi2": [904.5]}, "FT/T1/X1/HL1/Q3/M0": {"Tx": ["-0.2132,"], "Ty": ["-0.0001496,"], "Tz": ["-0.5926,"], "Rx": ["-0.0002985,"], "Ry": ["-1.954e-07,"], "Rz": ["0.0002046"], "x_global": ["265"], "y_global": ["1213"], "z_global": ["7830"], "average_hit_x": ["271"], "average_hit_y": ["354.9"], "average_hit_z": ["7826"], "nTracks": ["698344"], "nHits": ["698344"], "localDeltaChi2": [1057.0]}, "FT/T1/X1/HL1/Q3/M1": {"Tx": ["-0.6675,"], "Ty": ["-0.002284,"], "Tz": ["-1.441,"], "Rx": ["-0.0008689,"], "Ry": ["-1.595e-07,"], "Rz": ["0.0002807"], "x_global": ["795"], "y_global": ["1213"], "z_global": ["7830"], "average_hit_x": ["758.9"], "average_hit_y": ["402.8"], "average_hit_z": ["7826"], "nTracks": ["473752"], "nHits": ["473752"], "localDeltaChi2": [518.5]}, "FT/T1/X1/HL1/Q3/M2": {"Tx": ["-0.7095,"], "Ty": ["-0.004027,"], "Tz": ["-1.63,"], "Rx": ["-0.001259,"], "Ry": ["-2.504e-07,"], "Rz": ["0.000372"], "x_global": ["1325"], "y_global": ["1213"], "z_global": ["7830"], "average_hit_x": ["1275"], "average_hit_y": ["554.3"], "average_hit_z": ["7826"], "nTracks": ["197255"], "nHits": ["197255"], "localDeltaChi2": [386.4]}, "FT/T1/X1/HL1/Q3/M3": {"Tx": ["-0.8989,"], "Ty": ["-0.006307,"], "Tz": ["-2.064,"], "Rx": ["-0.001525,"], "Ry": ["1.901e-07,"], "Rz": ["0.000501"], "x_global": ["1855"], "y_global": ["1213"], "z_global": ["7830"], "average_hit_x": ["1810"], "average_hit_y": ["655.4"], "average_hit_z": ["7826"], "nTracks": ["69632"], "nHits": ["69632"], "localDeltaChi2": [464.85]}, "FT/T1/X1/HL1/Q3/M4": {"Tx": ["-1.041,"], "Ty": ["-0.00798,"], "Tz": ["-2.425,"], "Rx": ["-0.001649,"], "Ry": ["3.03e-07,"], "Rz": ["0.0005045"], "x_global": ["2385"], "y_global": ["1213"], "z_global": ["7830"], "average_hit_x": ["2193"], "average_hit_y": ["599"], "average_hit_z": ["7826"], "nTracks": ["9233"], "nHits": ["9233"], "localDeltaChi2": [905.0]}, "FT/T1/X2/HL0/Q0/M0": {"Tx": ["-0.3391,"], "Ty": ["-0.002863,"], "Tz": ["-1.06,"], "Rx": ["-0.001416,"], "Ry": ["3.431e-07,"], "Rz": ["0.0004388"], "x_global": ["-265"], "y_global": ["-1213"], "z_global": ["8032"], "average_hit_x": ["-263.5"], "average_hit_y": ["-349.5"], "average_hit_z": ["8037"], "nTracks": ["495460"], "nHits": ["495460"], "localDeltaChi2": [1102.5]}, "FT/T1/X2/HL0/Q0/M1": {"Tx": ["0.003531,"], "Ty": ["-0.0004511,"], "Tz": ["-0.6536,"], "Rx": ["-8.971e-05,"], "Ry": ["5.306e-08,"], "Rz": ["8.947e-05"], "x_global": ["-795"], "y_global": ["-1213"], "z_global": ["8032"], "average_hit_x": ["-771.1"], "average_hit_y": ["-420.3"], "average_hit_z": ["8035"], "nTracks": ["565951"], "nHits": ["565951"], "localDeltaChi2": [2163.0]}, "FT/T1/X2/HL0/Q0/M2": {"Tx": ["-0.2069,"], "Ty": ["-0.0004048,"], "Tz": ["-0.5511,"], "Rx": ["-0.000169,"], "Ry": ["1.02e-07,"], "Rz": ["8.479e-05"], "x_global": ["-1325"], "y_global": ["-1213"], "z_global": ["8032"], "average_hit_x": ["-1268"], "average_hit_y": ["-569.1"], "average_hit_z": ["8036"], "nTracks": ["211481"], "nHits": ["211481"], "localDeltaChi2": [2839.5]}, "FT/T1/X2/HL0/Q0/M3": {"Tx": ["0.128,"], "Ty": ["-0.0003567,"], "Tz": ["-0.3181,"], "Rx": ["0.0001881,"], "Ry": ["1.046e-07,"], "Rz": ["2.692e-05"], "x_global": ["-1855"], "y_global": ["-1213"], "z_global": ["8032"], "average_hit_x": ["-1842"], "average_hit_y": ["-669.5"], "average_hit_z": ["8035"], "nTracks": ["61160"], "nHits": ["61160"], "localDeltaChi2": [2937.5]}, "FT/T1/X2/HL0/Q0/M4": {"Tx": ["0.2373,"], "Ty": ["-0.0003565,"], "Tz": ["-0.124,"], "Rx": ["0.0001234,"], "Ry": ["-5.037e-08,"], "Rz": ["1.582e-05"], "x_global": ["-2385"], "y_global": ["-1213"], "z_global": ["8032"], "average_hit_x": ["-2229"], "average_hit_y": ["-611.3"], "average_hit_z": ["8036"], "nTracks": ["15741"], "nHits": ["15741"], "localDeltaChi2": [3476.0]}, "FT/T1/X2/HL0/Q2/M0": {"Tx": ["-0.1462,"], "Ty": ["-0.001216,"], "Tz": ["0.5299,"], "Rx": ["-0.0001125,"], "Ry": ["5.009e-07,"], "Rz": ["-3.862e-05"], "x_global": ["-265"], "y_global": ["1213"], "z_global": ["8040"], "average_hit_x": ["-170.7"], "average_hit_y": ["348"], "average_hit_z": ["8036"], "nTracks": ["218042"], "nHits": ["218042"], "localDeltaChi2": [1106.0]}, "FT/T1/X2/HL0/Q2/M1": {"Tx": ["-0.3582,"], "Ty": ["-0.001512,"], "Tz": ["-0.01984,"], "Rx": ["0.0004342,"], "Ry": ["-3.688e-07,"], "Rz": ["0.000203"], "x_global": ["-795"], "y_global": ["1213"], "z_global": ["8040"], "average_hit_x": ["-789.3"], "average_hit_y": ["154"], "average_hit_z": ["8035"], "nTracks": ["165904"], "nHits": ["165904"], "localDeltaChi2": [2161.0]}, "FT/T1/X2/HL0/Q2/M2": {"Tx": ["-0.1559,"], "Ty": ["-0.0008808,"], "Tz": ["0.2702,"], "Rx": ["0.0005105,"], "Ry": ["-1.097e-07,"], "Rz": ["0.0002144"], "x_global": ["-1325"], "y_global": ["1213"], "z_global": ["8040"], "average_hit_x": ["-1282"], "average_hit_y": ["220.7"], "average_hit_z": ["8035"], "nTracks": ["86423"], "nHits": ["86423"], "localDeltaChi2": [2838.0]}, "FT/T1/X2/HL0/Q2/M3": {"Tx": ["-0.5177,"], "Ty": ["0.0006413,"], "Tz": ["-0.1038,"], "Rx": ["0.0003654,"], "Ry": ["5.608e-08,"], "Rz": ["0.0002944"], "x_global": ["-1855"], "y_global": ["1213"], "z_global": ["8040"], "average_hit_x": ["-1806"], "average_hit_y": ["336"], "average_hit_z": ["8035"], "nTracks": ["29361"], "nHits": ["29361"], "localDeltaChi2": [2937.0]}, "FT/T1/X2/HL0/Q2/M4": {"Tx": ["-0.1577,"], "Ty": ["0.001391,"], "Tz": ["-0.398,"], "Rx": ["-0.0001025,"], "Ry": ["-3.499e-08,"], "Rz": ["-8.148e-05"], "x_global": ["-2385"], "y_global": ["1213"], "z_global": ["8040"], "average_hit_x": ["-2227"], "average_hit_y": ["405.7"], "average_hit_z": ["8036"], "nTracks": ["6672"], "nHits": ["6672"], "localDeltaChi2": [3476.0]}, "FT/T1/X2/HL1/Q1/M0": {"Tx": ["-0.1534,"], "Ty": ["-0.0001943,"], "Tz": ["0.3414,"], "Rx": ["8.707e-05,"], "Ry": ["-1.199e-07,"], "Rz": ["-4.716e-05"], "x_global": ["265"], "y_global": ["-1213"], "z_global": ["8032"], "average_hit_x": ["218.1"], "average_hit_y": ["-332.5"], "average_hit_z": ["8036"], "nTracks": ["423822"], "nHits": ["423822"], "localDeltaChi2": [1240.0]}, "FT/T1/X2/HL1/Q1/M1": {"Tx": ["-0.731,"], "Ty": ["1.129e-05,"], "Tz": ["-0.2369,"], "Rx": ["0.0005372,"], "Ry": ["-3.105e-07,"], "Rz": ["0.0002108"], "x_global": ["795"], "y_global": ["-1213"], "z_global": ["8032"], "average_hit_x": ["777.3"], "average_hit_y": ["-163.8"], "average_hit_z": ["8035"], "nTracks": ["178451"], "nHits": ["178451"], "localDeltaChi2": [531.5]}, "FT/T1/X2/HL1/Q1/M2": {"Tx": ["-0.799,"], "Ty": ["0.0006051,"], "Tz": ["-0.7196,"], "Rx": ["0.0006774,"], "Ry": ["1.385e-08,"], "Rz": ["0.0004347"], "x_global": ["1325"], "y_global": ["-1213"], "z_global": ["8032"], "average_hit_x": ["1277"], "average_hit_y": ["-221.1"], "average_hit_z": ["8034"], "nTracks": ["75258"], "nHits": ["75258"], "localDeltaChi2": [1673.5]}, "FT/T1/X2/HL1/Q1/M3": {"Tx": ["0.3706,"], "Ty": ["0.0008141,"], "Tz": ["-0.6882,"], "Rx": ["0.0003021,"], "Ry": ["-9.298e-08,"], "Rz": ["-0.0008387"], "x_global": ["1855"], "y_global": ["-1213"], "z_global": ["8032"], "average_hit_x": ["1826"], "average_hit_y": ["-342.2"], "average_hit_z": ["8035"], "nTracks": ["36201"], "nHits": ["36201"], "localDeltaChi2": [694.5]}, "FT/T1/X2/HL1/Q1/M4": {"Tx": ["0.5448,"], "Ty": ["-0.002116,"], "Tz": ["-1.701,"], "Rx": ["-0.0006699,"], "Ry": ["2.521e-07,"], "Rz": ["-0.0007306"], "x_global": ["2385"], "y_global": ["-1213"], "z_global": ["8032"], "average_hit_x": ["2248"], "average_hit_y": ["-422.1"], "average_hit_z": ["8035"], "nTracks": ["8342"], "nHits": ["8342"], "localDeltaChi2": [2689.0]}, "FT/T1/X2/HL1/Q3/M0": {"Tx": ["0.3327,"], "Ty": ["0.0001988,"], "Tz": ["0.235,"], "Rx": ["3.304e-06,"], "Ry": ["-4.812e-09,"], "Rz": ["-0.0001008"], "x_global": ["265"], "y_global": ["1213"], "z_global": ["8040"], "average_hit_x": ["266.8"], "average_hit_y": ["362.4"], "average_hit_z": ["8036"], "nTracks": ["678510"], "nHits": ["678510"], "localDeltaChi2": [1252.5]}, "FT/T1/X2/HL1/Q3/M1": {"Tx": ["0.5124,"], "Ty": ["0.0003836,"], "Tz": ["-0.04324,"], "Rx": ["0.0006991,"], "Ry": ["-4.002e-07,"], "Rz": ["-3.046e-05"], "x_global": ["795"], "y_global": ["1213"], "z_global": ["8040"], "average_hit_x": ["762.5"], "average_hit_y": ["404.5"], "average_hit_z": ["8035"], "nTracks": ["482247"], "nHits": ["482247"], "localDeltaChi2": [541.0]}, "FT/T1/X2/HL1/Q3/M2": {"Tx": ["0.38,"], "Ty": ["0.0007217,"], "Tz": ["-0.185,"], "Rx": ["0.001107,"], "Ry": ["-8.161e-07,"], "Rz": ["-8.922e-05"], "x_global": ["1325"], "y_global": ["1213"], "z_global": ["8040"], "average_hit_x": ["1278"], "average_hit_y": ["542.5"], "average_hit_z": ["8034"], "nTracks": ["209317"], "nHits": ["209317"], "localDeltaChi2": [1678.0]}, "FT/T1/X2/HL1/Q3/M3": {"Tx": ["0.688,"], "Ty": ["0.00073,"], "Tz": ["-0.281,"], "Rx": ["0.0006418,"], "Ry": ["-2.869e-07,"], "Rz": ["-3.421e-05"], "x_global": ["1855"], "y_global": ["1213"], "z_global": ["8040"], "average_hit_x": ["1813"], "average_hit_y": ["678.6"], "average_hit_z": ["8035"], "nTracks": ["74788"], "nHits": ["74788"], "localDeltaChi2": [698.0]}, "FT/T1/X2/HL1/Q3/M4": {"Tx": ["0.4361,"], "Ty": ["-0.0009519,"], "Tz": ["0.5372,"], "Rx": ["0.001175,"], "Ry": ["-5.811e-07,"], "Rz": ["-7.815e-05"], "x_global": ["2385"], "y_global": ["1213"], "z_global": ["8040"], "average_hit_x": ["2228"], "average_hit_y": ["630"], "average_hit_z": ["8035"], "nTracks": ["15470"], "nHits": ["15470"], "localDeltaChi2": [2689.5]}, "FT/T2/U/HL0/Q0/M0": {"Tx": ["0.3721,"], "Ty": ["0.001363,"], "Tz": ["1.379,"], "Rx": ["-0.0003769,"], "Ry": ["-1.69e-07,"], "Rz": ["-2.12e-05"], "x_global": ["-371.7"], "y_global": ["-1208"], "z_global": ["8574"], "average_hit_x": ["-293.3"], "average_hit_y": ["-380.1"], "average_hit_z": ["8580"], "nTracks": ["429989"], "nHits": ["429989"], "localDeltaChi2": [1049.5]}, "FT/T2/U/HL0/Q0/M1": {"Tx": ["0.3048,"], "Ty": ["-0.000702,"], "Tz": ["1.356,"], "Rx": ["0.0003661,"], "Ry": ["3.432e-08,"], "Rz": ["-4.458e-05"], "x_global": ["-903.7"], "y_global": ["-1208"], "z_global": ["8574"], "average_hit_x": ["-821.1"], "average_hit_y": ["-440.4"], "average_hit_z": ["8578"], "nTracks": ["525161"], "nHits": ["525161"], "localDeltaChi2": [6340.0]}, "FT/T2/U/HL0/Q0/M2": {"Tx": ["0.3027,"], "Ty": ["0.0003288,"], "Tz": ["1.055,"], "Rx": ["-3.968e-05,"], "Ry": ["6.117e-08,"], "Rz": ["-7.701e-05"], "x_global": ["-1436"], "y_global": ["-1208"], "z_global": ["8574"], "average_hit_x": ["-1327"], "average_hit_y": ["-552"], "average_hit_z": ["8579"], "nTracks": ["239654"], "nHits": ["239654"], "localDeltaChi2": [5025.0]}, "FT/T2/U/HL0/Q0/M3": {"Tx": ["-0.3287,"], "Ty": ["-0.0002823,"], "Tz": ["-0.1078,"], "Rx": ["-0.0007149,"], "Ry": ["1.458e-07,"], "Rz": ["0.0002602"], "x_global": ["-1968"], "y_global": ["-1208"], "z_global": ["8574"], "average_hit_x": ["-1891"], "average_hit_y": ["-673.7"], "average_hit_z": ["8579"], "nTracks": ["64531"], "nHits": ["64531"], "localDeltaChi2": [5000.0]}, "FT/T2/U/HL0/Q0/M4": {"Tx": ["0.1654,"], "Ty": ["0.0007827,"], "Tz": ["0.5062,"], "Rx": ["-0.0008064,"], "Ry": ["-8.273e-08,"], "Rz": ["0.0002275"], "x_global": ["-2500"], "y_global": ["-1208"], "z_global": ["8574"], "average_hit_x": ["-2359"], "average_hit_y": ["-611.7"], "average_hit_z": ["8579"], "nTracks": ["27839"], "nHits": ["27839"], "localDeltaChi2": [4748.0]}, "FT/T2/U/HL0/Q2/M0": {"Tx": ["-0.06295,"], "Ty": ["-2.843e-05,"], "Tz": ["1.904,"], "Rx": ["5.505e-05,"], "Ry": ["-7.88e-08,"], "Rz": ["-0.0002337"], "x_global": ["-160.3"], "y_global": ["1208"], "z_global": ["8582"], "average_hit_x": ["-157.1"], "average_hit_y": ["429.3"], "average_hit_z": ["8580"], "nTracks": ["259360"], "nHits": ["259360"], "localDeltaChi2": [1053.0]}, "FT/T2/U/HL0/Q2/M1": {"Tx": ["-0.06811,"], "Ty": ["0.0006025,"], "Tz": ["0.7435,"], "Rx": ["-0.0001397,"], "Ry": ["9.561e-08,"], "Rz": ["-0.0001505"], "x_global": ["-692.3"], "y_global": ["1208"], "z_global": ["8582"], "average_hit_x": ["-782.9"], "average_hit_y": ["176.8"], "average_hit_z": ["8579"], "nTracks": ["145233"], "nHits": ["145233"], "localDeltaChi2": [6335.0]}, "FT/T2/U/HL0/Q2/M2": {"Tx": ["0.5077,"], "Ty": ["0.0001311,"], "Tz": ["0.4507,"], "Rx": ["-0.0005409,"], "Ry": ["2.722e-08,"], "Rz": ["-0.0005912"], "x_global": ["-1224"], "y_global": ["1208"], "z_global": ["8582"], "average_hit_x": ["-1269"], "average_hit_y": ["202.7"], "average_hit_z": ["8580"], "nTracks": ["93986"], "nHits": ["93986"], "localDeltaChi2": [5020.0]}, "FT/T2/U/HL0/Q2/M3": {"Tx": ["-0.583,"], "Ty": ["0.000245,"], "Tz": ["0.9755,"], "Rx": ["0.0001817,"], "Ry": ["1.328e-08,"], "Rz": ["0.0004916"], "x_global": ["-1756"], "y_global": ["1208"], "z_global": ["8582"], "average_hit_x": ["-1797"], "average_hit_y": ["318.8"], "average_hit_z": ["8579"], "nTracks": ["39090"], "nHits": ["39090"], "localDeltaChi2": [4999.5]}, "FT/T2/U/HL0/Q2/M4": {"Tx": ["-0.4363,"], "Ty": ["0.0006942,"], "Tz": ["1.142,"], "Rx": ["-0.0002813,"], "Ry": ["-3.216e-07,"], "Rz": ["-4.077e-06"], "x_global": ["-2288"], "y_global": ["1208"], "z_global": ["8582"], "average_hit_x": ["-2326"], "average_hit_y": ["410.9"], "average_hit_z": ["8580"], "nTracks": ["13493"], "nHits": ["13493"], "localDeltaChi2": [4747.5]}, "FT/T2/U/HL1/Q1/M0": {"Tx": ["0.0772,"], "Ty": ["-0.0007896,"], "Tz": ["1.295,"], "Rx": ["0.000285,"], "Ry": ["-1.959e-07,"], "Rz": ["-0.0001153"], "x_global": ["160.3"], "y_global": ["-1208"], "z_global": ["8574"], "average_hit_x": ["208.4"], "average_hit_y": ["-383.8"], "average_hit_z": ["8579"], "nTracks": ["456464"], "nHits": ["456464"], "localDeltaChi2": [2088.5]}, "FT/T2/U/HL1/Q1/M1": {"Tx": ["-1.113,"], "Ty": ["-0.001485,"], "Tz": ["1.585,"], "Rx": ["0.0001526,"], "Ry": ["2.468e-07,"], "Rz": ["0.0004587"], "x_global": ["692.3"], "y_global": ["-1208"], "z_global": ["8574"], "average_hit_x": ["761"], "average_hit_y": ["-197"], "average_hit_z": ["8579"], "nTracks": ["174554"], "nHits": ["174554"], "localDeltaChi2": [203.0]}, "FT/T2/U/HL1/Q1/M2": {"Tx": ["0.1357,"], "Ty": ["0.0003128,"], "Tz": ["0.02242,"], "Rx": ["-0.0006788,"], "Ry": ["2.037e-08,"], "Rz": ["-0.0006069"], "x_global": ["1224"], "y_global": ["-1208"], "z_global": ["8574"], "average_hit_x": ["1275"], "average_hit_y": ["-207.3"], "average_hit_z": ["8580"], "nTracks": ["98754"], "nHits": ["98754"], "localDeltaChi2": [73.15]}, "FT/T2/U/HL1/Q1/M3": {"Tx": ["0.4101,"], "Ty": ["-9.366e-05,"], "Tz": ["-0.004978,"], "Rx": ["-0.0003136,"], "Ry": ["4.528e-08,"], "Rz": ["-0.0006053"], "x_global": ["1756"], "y_global": ["-1208"], "z_global": ["8574"], "average_hit_x": ["1810"], "average_hit_y": ["-319.7"], "average_hit_z": ["8579"], "nTracks": ["38076"], "nHits": ["38076"], "localDeltaChi2": [64.4]}, "FT/T2/U/HL1/Q1/M4": {"Tx": ["0.9097,"], "Ty": ["-0.001558,"], "Tz": ["-0.5716,"], "Rx": ["-0.001024,"], "Ry": ["1.608e-07,"], "Rz": ["-0.00131"], "x_global": ["2288"], "y_global": ["-1208"], "z_global": ["8574"], "average_hit_x": ["2322"], "average_hit_y": ["-422.1"], "average_hit_z": ["8579"], "nTracks": ["19400"], "nHits": ["19400"], "localDeltaChi2": [96.4]}, "FT/T2/U/HL1/Q3/M0": {"Tx": ["0.5598,"], "Ty": ["0.000251,"], "Tz": ["1.005,"], "Rx": ["5.216e-05,"], "Ry": ["-3.106e-08,"], "Rz": ["-0.00041"], "x_global": ["371.7"], "y_global": ["1208"], "z_global": ["8582"], "average_hit_x": ["287.5"], "average_hit_y": ["378.9"], "average_hit_z": ["8579"], "nTracks": ["612519"], "nHits": ["612519"], "localDeltaChi2": [2100.0]}, "FT/T2/U/HL1/Q3/M1": {"Tx": ["0.2711,"], "Ty": ["0.001048,"], "Tz": ["1.209,"], "Rx": ["-0.000163,"], "Ry": ["6.209e-08,"], "Rz": ["0.0002356"], "x_global": ["903.7"], "y_global": ["1208"], "z_global": ["8582"], "average_hit_x": ["811.8"], "average_hit_y": ["423.3"], "average_hit_z": ["8579"], "nTracks": ["453327"], "nHits": ["453327"], "localDeltaChi2": [212.5]}, "FT/T2/U/HL1/Q3/M2": {"Tx": ["0.4975,"], "Ty": ["0.0006282,"], "Tz": ["0.8354,"], "Rx": ["-4.498e-06,"], "Ry": ["-5.483e-08,"], "Rz": ["8.476e-05"], "x_global": ["1436"], "y_global": ["1208"], "z_global": ["8582"], "average_hit_x": ["1342"], "average_hit_y": ["540.7"], "average_hit_z": ["8579"], "nTracks": ["230019"], "nHits": ["230019"], "localDeltaChi2": [81.6]}, "FT/T2/U/HL1/Q3/M3": {"Tx": ["0.04419,"], "Ty": ["0.000433,"], "Tz": ["-0.07379,"], "Rx": ["-0.0003698,"], "Ry": ["1.545e-07,"], "Rz": ["0.0002307"], "x_global": ["1968"], "y_global": ["1208"], "z_global": ["8582"], "average_hit_x": ["1880"], "average_hit_y": ["675.4"], "average_hit_z": ["8579"], "nTracks": ["84703"], "nHits": ["84703"], "localDeltaChi2": [68.85]}, "FT/T2/U/HL1/Q3/M4": {"Tx": ["0.5754,"], "Ty": ["0.0008591,"], "Tz": ["0.681,"], "Rx": ["1.114e-05,"], "Ry": ["-2.176e-08,"], "Rz": ["8.598e-05"], "x_global": ["2500"], "y_global": ["1208"], "z_global": ["8582"], "average_hit_x": ["2361"], "average_hit_y": ["636.2"], "average_hit_z": ["8579"], "nTracks": ["28072"], "nHits": ["28072"], "localDeltaChi2": [97.95]}, "FT/T2/V/HL0/Q0/M0": {"Tx": ["-0.6424,"], "Ty": ["0.002147,"], "Tz": ["-0.767,"], "Rx": ["0.0005313,"], "Ry": ["-6.331e-06,"], "Rz": ["-0.000105"], "x_global": ["-160.3"], "y_global": ["-1208"], "z_global": ["8644"], "average_hit_x": ["-219"], "average_hit_y": ["-390.1"], "average_hit_z": ["8649"], "nTracks": ["427694"], "nHits": ["427694"], "localDeltaChi2": [1089.5]}, "FT/T2/V/HL0/Q0/M1": {"Tx": ["-1.158,"], "Ty": ["-0.001642,"], "Tz": ["-2.098,"], "Rx": ["-0.00065,"], "Ry": ["-2.011e-06,"], "Rz": ["0.0001643"], "x_global": ["-692.3"], "y_global": ["-1208"], "z_global": ["8644"], "average_hit_x": ["-759.7"], "average_hit_y": ["-417.4"], "average_hit_z": ["8648"], "nTracks": ["509019"], "nHits": ["509019"], "localDeltaChi2": [4627.5]}, "FT/T2/V/HL0/Q0/M2": {"Tx": ["-0.9113,"], "Ty": ["0.0002137,"], "Tz": ["-0.5538,"], "Rx": ["-0.0003221,"], "Ry": ["1.197e-07,"], "Rz": ["-2.715e-05"], "x_global": ["-1224"], "y_global": ["-1208"], "z_global": ["8644"], "average_hit_x": ["-1240"], "average_hit_y": ["-552.4"], "average_hit_z": ["8648"], "nTracks": ["282269"], "nHits": ["282269"], "localDeltaChi2": [4891.5]}, "FT/T2/V/HL0/Q0/M3": {"Tx": ["-0.7537,"], "Ty": ["0.000443,"], "Tz": ["-0.7893,"], "Rx": ["-0.0009585,"], "Ry": ["-3.072e-07,"], "Rz": ["0.0002187"], "x_global": ["-1756"], "y_global": ["-1208"], "z_global": ["8644"], "average_hit_x": ["-1657"], "average_hit_y": ["-720.6"], "average_hit_z": ["8648"], "nTracks": ["55264"], "nHits": ["55264"], "localDeltaChi2": [8025.0]}, "FT/T2/V/HL0/Q0/M4": {"Tx": ["-1.409,"], "Ty": ["0.0005513,"], "Tz": ["-0.5454,"], "Rx": ["-2.538e-05,"], "Ry": ["-1.835e-07,"], "Rz": ["0.0003533"], "x_global": ["-2288"], "y_global": ["-1208"], "z_global": ["8644"], "average_hit_x": ["-2286"], "average_hit_y": ["-752.5"], "average_hit_z": ["8649"], "nTracks": ["42146"], "nHits": ["42146"], "localDeltaChi2": [5665.0]}, "FT/T2/V/HL0/Q2/M0": {"Tx": ["0.5135,"], "Ty": ["0.001109,"], "Tz": ["-1.52,"], "Rx": ["-8.606e-05,"], "Ry": ["8.244e-06,"], "Rz": ["0.0002113"], "x_global": ["-371.7"], "y_global": ["1208"], "z_global": ["8652"], "average_hit_x": ["-214.9"], "average_hit_y": ["369.4"], "average_hit_z": ["8649"], "nTracks": ["208871"], "nHits": ["208871"], "localDeltaChi2": [1092.0]}, "FT/T2/V/HL0/Q2/M1": {"Tx": ["-0.3508,"], "Ty": ["0.002127,"], "Tz": ["-1.093,"], "Rx": ["0.0001776,"], "Ry": ["1.096e-05,"], "Rz": ["0.00108"], "x_global": ["-903.7"], "y_global": ["1208"], "z_global": ["8652"], "average_hit_x": ["-815.3"], "average_hit_y": ["176.1"], "average_hit_z": ["8649"], "nTracks": ["145992"], "nHits": ["145992"], "localDeltaChi2": [4625.0]}, "FT/T2/V/HL0/Q2/M2": {"Tx": ["0.9507,"], "Ty": ["-0.003014,"], "Tz": ["-1.64,"], "Rx": ["-0.001217,"], "Ry": ["-1.658e-06,"], "Rz": ["-5.3e-06"], "x_global": ["-1436"], "y_global": ["1208"], "z_global": ["8652"], "average_hit_x": ["-1311"], "average_hit_y": ["210.3"], "average_hit_z": ["8648"], "nTracks": ["96947"], "nHits": ["96947"], "localDeltaChi2": [4890.0]}, "FT/T2/V/HL0/Q2/M3": {"Tx": ["1.574,"], "Ty": ["-0.02072,"], "Tz": ["3.85,"], "Rx": ["0.002863,"], "Ry": ["1.796e-06,"], "Rz": ["-0.0008952"], "x_global": ["-1968"], "y_global": ["1208"], "z_global": ["8652"], "average_hit_x": ["-1846"], "average_hit_y": ["332.7"], "average_hit_z": ["8651"], "nTracks": ["19890"], "nHits": ["19890"], "localDeltaChi2": [8020.0]}, "FT/T2/V/HL0/Q2/M4": {"Tx": ["0.5521,"], "Ty": ["-0.002397,"], "Tz": ["1.098,"], "Rx": ["0.001329,"], "Ry": ["5.562e-06,"], "Rz": ["0.0003533"], "x_global": ["-2500"], "y_global": ["1208"], "z_global": ["8652"], "average_hit_x": ["-2380"], "average_hit_y": ["405.1"], "average_hit_z": ["8649"], "nTracks": ["11404"], "nHits": ["11404"], "localDeltaChi2": [5665.0]}, "FT/T2/V/HL1/Q1/M0": {"Tx": ["-0.599,"], "Ty": ["-0.002938,"], "Tz": ["0.9557,"], "Rx": ["0.001304,"], "Ry": ["1.434e-06,"], "Rz": ["-2.062e-05"], "x_global": ["371.7"], "y_global": ["-1208"], "z_global": ["8644"], "average_hit_x": ["257.2"], "average_hit_y": ["-347.5"], "average_hit_z": ["8648"], "nTracks": ["413887"], "nHits": ["413887"], "localDeltaChi2": [2052.0]}, "FT/T2/V/HL1/Q1/M1": {"Tx": ["-0.5733,"], "Ty": ["-0.0005575,"], "Tz": ["0.05869,"], "Rx": ["0.0001004,"], "Ry": ["1.499e-07,"], "Rz": ["0.000315"], "x_global": ["903.7"], "y_global": ["-1208"], "z_global": ["8644"], "average_hit_x": ["800.2"], "average_hit_y": ["-185.6"], "average_hit_z": ["8647"], "nTracks": ["169010"], "nHits": ["169010"], "localDeltaChi2": [918.0]}, "FT/T2/V/HL1/Q1/M2": {"Tx": ["0.02517,"], "Ty": ["0.0002258,"], "Tz": ["0.12,"], "Rx": ["-0.000346,"], "Ry": ["-2.569e-07,"], "Rz": ["4.402e-05"], "x_global": ["1436"], "y_global": ["-1208"], "z_global": ["8644"], "average_hit_x": ["1313"], "average_hit_y": ["-209"], "average_hit_z": ["8647"], "nTracks": ["98808"], "nHits": ["98808"], "localDeltaChi2": [472.25]}, "FT/T2/V/HL1/Q1/M3": {"Tx": ["-0.4082,"], "Ty": ["-0.0002106,"], "Tz": ["0.9343,"], "Rx": ["0.0001566,"], "Ry": ["1.649e-07,"], "Rz": ["0.0004913"], "x_global": ["1968"], "y_global": ["-1208"], "z_global": ["8644"], "average_hit_x": ["1867"], "average_hit_y": ["-327.8"], "average_hit_z": ["8648"], "nTracks": ["36591"], "nHits": ["36591"], "localDeltaChi2": [185.05]}, "FT/T2/V/HL1/Q1/M4": {"Tx": ["-2.15,"], "Ty": ["-0.01282,"], "Tz": ["3.375,"], "Rx": ["0.001316,"], "Ry": ["1.066e-06,"], "Rz": ["0.001632"], "x_global": ["2500"], "y_global": ["-1208"], "z_global": ["8644"], "average_hit_x": ["2375"], "average_hit_y": ["-410.8"], "average_hit_z": ["8648"], "nTracks": ["17558"], "nHits": ["17558"], "localDeltaChi2": [466.95]}, "FT/T2/V/HL1/Q3/M0": {"Tx": ["0.2684,"], "Ty": ["-0.0002473,"], "Tz": ["0.2474,"], "Rx": ["0.0007245,"], "Ry": ["1.366e-07,"], "Rz": ["0.0002932"], "x_global": ["160.3"], "y_global": ["1208"], "z_global": ["8652"], "average_hit_x": ["231.8"], "average_hit_y": ["384.4"], "average_hit_z": ["8648"], "nTracks": ["598241"], "nHits": ["598241"], "localDeltaChi2": [2063.5]}, "FT/T2/V/HL1/Q3/M1": {"Tx": ["-0.07561,"], "Ty": ["-0.0002255,"], "Tz": ["0.4276,"], "Rx": ["0.0004035,"], "Ry": ["-1.079e-08,"], "Rz": ["0.00022"], "x_global": ["692.3"], "y_global": ["1208"], "z_global": ["8652"], "average_hit_x": ["747"], "average_hit_y": ["412.4"], "average_hit_z": ["8648"], "nTracks": ["469196"], "nHits": ["469196"], "localDeltaChi2": [928.5]}, "FT/T2/V/HL1/Q3/M2": {"Tx": ["-0.1814,"], "Ty": ["0.0001488,"], "Tz": ["0.5945,"], "Rx": ["4.735e-05,"], "Ry": ["-1.067e-08,"], "Rz": ["8.48e-05"], "x_global": ["1224"], "y_global": ["1208"], "z_global": ["8652"], "average_hit_x": ["1256"], "average_hit_y": ["531.9"], "average_hit_z": ["8648"], "nTracks": ["249790"], "nHits": ["249790"], "localDeltaChi2": [479.1]}, "FT/T2/V/HL1/Q3/M3": {"Tx": ["-0.2587,"], "Ty": ["0.000267,"], "Tz": ["0.7562,"], "Rx": ["8.381e-06,"], "Ry": ["-1.378e-08,"], "Rz": ["5.86e-05"], "x_global": ["1756"], "y_global": ["1208"], "z_global": ["8652"], "average_hit_x": ["1763"], "average_hit_y": ["723.9"], "average_hit_z": ["8647"], "nTracks": ["102103"], "nHits": ["102103"], "localDeltaChi2": [188.5]}, "FT/T2/V/HL1/Q3/M4": {"Tx": ["-0.5153,"], "Ty": ["0.0005915,"], "Tz": ["0.1815,"], "Rx": ["-0.001319,"], "Ry": ["-2.838e-07,"], "Rz": ["0.0005656"], "x_global": ["2288"], "y_global": ["1208"], "z_global": ["8652"], "average_hit_x": ["2287"], "average_hit_y": ["763"], "average_hit_z": ["8646"], "nTracks": ["44187"], "nHits": ["44187"], "localDeltaChi2": [468.55]}, "FT/T2/X1/HL0/Q0/M0": {"Tx": ["-0.2766,"], "Ty": ["0.0003726,"], "Tz": ["-0.1274,"], "Rx": ["0.0003238,"], "Ry": ["-5.388e-08,"], "Rz": ["0.0001635"], "x_global": ["-265"], "y_global": ["-1213"], "z_global": ["8504"], "average_hit_x": ["-256.4"], "average_hit_y": ["-369.5"], "average_hit_z": ["8509"], "nTracks": ["428776"], "nHits": ["428776"], "localDeltaChi2": [1388.5]}, "FT/T2/X1/HL0/Q0/M1": {"Tx": ["-0.4638,"], "Ty": ["0.0001438,"], "Tz": ["0.3294,"], "Rx": ["-0.0001078,"], "Ry": ["7.428e-08,"], "Rz": ["-3.772e-05"], "x_global": ["-795"], "y_global": ["-1213"], "z_global": ["8504"], "average_hit_x": ["-782.3"], "average_hit_y": ["-430.8"], "average_hit_z": ["8508"], "nTracks": ["533302"], "nHits": ["533302"], "localDeltaChi2": [4716.0]}, "FT/T2/X1/HL0/Q0/M2": {"Tx": ["-0.6387,"], "Ty": ["4.082e-05,"], "Tz": ["-0.168,"], "Rx": ["9.01e-05,"], "Ry": ["9.977e-08,"], "Rz": ["9.604e-05"], "x_global": ["-1325"], "y_global": ["-1213"], "z_global": ["8504"], "average_hit_x": ["-1276"], "average_hit_y": ["-557"], "average_hit_z": ["8508"], "nTracks": ["256117"], "nHits": ["256117"], "localDeltaChi2": [4720.0]}, "FT/T2/X1/HL0/Q0/M3": {"Tx": ["-0.5236,"], "Ty": ["-2.053e-06,"], "Tz": ["-0.07434,"], "Rx": ["0.0002096,"], "Ry": ["1.287e-07,"], "Rz": ["-2.551e-05"], "x_global": ["-1855"], "y_global": ["-1213"], "z_global": ["8504"], "average_hit_x": ["-1818"], "average_hit_y": ["-699.6"], "average_hit_z": ["8508"], "nTracks": ["70888"], "nHits": ["70888"], "localDeltaChi2": [3935.0]}, "FT/T2/X1/HL0/Q0/M4": {"Tx": ["-0.6332,"], "Ty": ["0.0001249,"], "Tz": ["-0.1839,"], "Rx": ["0.0008081,"], "Ry": ["3.652e-07,"], "Rz": ["-0.0002268"], "x_global": ["-2385"], "y_global": ["-1213"], "z_global": ["8504"], "average_hit_x": ["-2308"], "average_hit_y": ["-676"], "average_hit_z": ["8509"], "nTracks": ["32809"], "nHits": ["32809"], "localDeltaChi2": [4871.5]}, "FT/T2/X1/HL0/Q2/M0": {"Tx": ["-0.221,"], "Ty": ["0.0004095,"], "Tz": ["-0.1878,"], "Rx": ["0.0002707,"], "Ry": ["3.279e-07,"], "Rz": ["0.0002468"], "x_global": ["-265"], "y_global": ["1213"], "z_global": ["8512"], "average_hit_x": ["-187.7"], "average_hit_y": ["384.6"], "average_hit_z": ["8509"], "nTracks": ["226590"], "nHits": ["226590"], "localDeltaChi2": [1391.5]}, "FT/T2/X1/HL0/Q2/M1": {"Tx": ["-0.4405,"], "Ty": ["-0.0002861,"], "Tz": ["-0.2466,"], "Rx": ["-0.0005795,"], "Ry": ["-8.972e-07,"], "Rz": ["0.0007834"], "x_global": ["-795"], "y_global": ["1213"], "z_global": ["8512"], "average_hit_x": ["-792.9"], "average_hit_y": ["170.6"], "average_hit_z": ["8508"], "nTracks": ["148514"], "nHits": ["148514"], "localDeltaChi2": [4711.0]}, "FT/T2/X1/HL0/Q2/M2": {"Tx": ["0.2332,"], "Ty": ["-0.0003606,"], "Tz": ["-0.6766,"], "Rx": ["-0.0003246,"], "Ry": ["-2.607e-07,"], "Rz": ["0.0002383"], "x_global": ["-1325"], "y_global": ["1213"], "z_global": ["8512"], "average_hit_x": ["-1284"], "average_hit_y": ["209.9"], "average_hit_z": ["8508"], "nTracks": ["95032"], "nHits": ["95032"], "localDeltaChi2": [4717.0]}, "FT/T2/X1/HL0/Q2/M3": {"Tx": ["0.5464,"], "Ty": ["-8.182e-05,"], "Tz": ["-0.5215,"], "Rx": ["-0.0001571,"], "Ry": ["-2.638e-07,"], "Rz": ["6.72e-06"], "x_global": ["-1855"], "y_global": ["1213"], "z_global": ["8512"], "average_hit_x": ["-1808"], "average_hit_y": ["319.2"], "average_hit_z": ["8508"], "nTracks": ["37536"], "nHits": ["37536"], "localDeltaChi2": [3934.0]}, "FT/T2/X1/HL0/Q2/M4": {"Tx": ["1.515,"], "Ty": ["-0.001234,"], "Tz": ["-1.653,"], "Rx": ["-0.0004017,"], "Ry": ["-1.82e-07,"], "Rz": ["-0.0005005"], "x_global": ["-2385"], "y_global": ["1213"], "z_global": ["8512"], "average_hit_x": ["-2322"], "average_hit_y": ["414.2"], "average_hit_z": ["8509"], "nTracks": ["11687"], "nHits": ["11687"], "localDeltaChi2": [4871.5]}, "FT/T2/X1/HL1/Q1/M0": {"Tx": ["-0.3954,"], "Ty": ["0.0001213,"], "Tz": ["-0.5623,"], "Rx": ["0.0004461,"], "Ry": ["3.11e-07,"], "Rz": ["0.0002806"], "x_global": ["265"], "y_global": ["-1213"], "z_global": ["8504"], "average_hit_x": ["227.1"], "average_hit_y": ["-365.1"], "average_hit_z": ["8509"], "nTracks": ["437847"], "nHits": ["437847"], "localDeltaChi2": [1857.5]}, "FT/T2/X1/HL1/Q1/M1": {"Tx": ["-0.3063,"], "Ty": ["-0.000687,"], "Tz": ["-0.5525,"], "Rx": ["-0.0004806,"], "Ry": ["-6.286e-07,"], "Rz": ["0.0004683"], "x_global": ["795"], "y_global": ["-1213"], "z_global": ["8504"], "average_hit_x": ["778.3"], "average_hit_y": ["-183.2"], "average_hit_z": ["8508"], "nTracks": ["171751"], "nHits": ["171751"], "localDeltaChi2": [528.0]}, "FT/T2/X1/HL1/Q1/M2": {"Tx": ["-1.154,"], "Ty": ["-0.0008857,"], "Tz": ["-0.7235,"], "Rx": ["-0.0002615,"], "Ry": ["-4.051e-07,"], "Rz": ["0.001271"], "x_global": ["1325"], "y_global": ["-1213"], "z_global": ["8504"], "average_hit_x": ["1291"], "average_hit_y": ["-189"], "average_hit_z": ["8508"], "nTracks": ["88346"], "nHits": ["88346"], "localDeltaChi2": [333.55]}, "FT/T2/X1/HL1/Q1/M3": {"Tx": ["-0.3301,"], "Ty": ["2.606e-06,"], "Tz": ["0.02907,"], "Rx": ["-1.87e-05,"], "Ry": ["1.964e-08,"], "Rz": ["0.0006241"], "x_global": ["1855"], "y_global": ["-1213"], "z_global": ["8504"], "average_hit_x": ["1827"], "average_hit_y": ["-326.1"], "average_hit_z": ["8508"], "nTracks": ["38062"], "nHits": ["38062"], "localDeltaChi2": [251.6]}, "FT/T2/X1/HL1/Q1/M4": {"Tx": ["-0.2624,"], "Ty": ["0.0001573,"], "Tz": ["-0.3293,"], "Rx": ["7.372e-05,"], "Ry": ["9.175e-08,"], "Rz": ["0.0007051"], "x_global": ["2385"], "y_global": ["-1213"], "z_global": ["8504"], "average_hit_x": ["2318"], "average_hit_y": ["-407.1"], "average_hit_z": ["8508"], "nTracks": ["17858"], "nHits": ["17858"], "localDeltaChi2": [605.5]}, "FT/T2/X1/HL1/Q3/M0": {"Tx": ["-0.2642,"], "Ty": ["-0.001584,"], "Tz": ["-1.73,"], "Rx": ["-0.0005096,"], "Ry": ["-3.448e-07,"], "Rz": ["0.0002632"], "x_global": ["265"], "y_global": ["1213"], "z_global": ["8512"], "average_hit_x": ["257.1"], "average_hit_y": ["382.1"], "average_hit_z": ["8508"], "nTracks": ["624189"], "nHits": ["624189"], "localDeltaChi2": [1872.5]}, "FT/T2/X1/HL1/Q3/M1": {"Tx": ["-0.3655,"], "Ty": ["0.0002444,"], "Tz": ["-0.04945,"], "Rx": ["-7.496e-05,"], "Ry": ["-6.999e-08,"], "Rz": ["8.559e-05"], "x_global": ["795"], "y_global": ["1213"], "z_global": ["8512"], "average_hit_x": ["774.2"], "average_hit_y": ["416.7"], "average_hit_z": ["8508"], "nTracks": ["467272"], "nHits": ["467272"], "localDeltaChi2": [540.5]}, "FT/T2/X1/HL1/Q3/M2": {"Tx": ["-0.7138,"], "Ty": ["3.578e-05,"], "Tz": ["-0.6137,"], "Rx": ["-0.0001826,"], "Ry": ["-4.506e-08,"], "Rz": ["0.0002693"], "x_global": ["1325"], "y_global": ["1213"], "z_global": ["8512"], "average_hit_x": ["1293"], "average_hit_y": ["534.6"], "average_hit_z": ["8508"], "nTracks": ["232139"], "nHits": ["232139"], "localDeltaChi2": [337.7]}, "FT/T2/X1/HL1/Q3/M3": {"Tx": ["-0.3387,"], "Ty": ["-0.0003724,"], "Tz": ["0.6628,"], "Rx": ["0.000505,"], "Ry": ["5.549e-08,"], "Rz": ["-7.267e-05"], "x_global": ["1855"], "y_global": ["1213"], "z_global": ["8512"], "average_hit_x": ["1813"], "average_hit_y": ["702.4"], "average_hit_z": ["8509"], "nTracks": ["88477"], "nHits": ["88477"], "localDeltaChi2": [256.9]}, "FT/T2/X1/HL1/Q3/M4": {"Tx": ["-0.4889,"], "Ty": ["0.0007116,"], "Tz": ["-0.2029,"], "Rx": ["0.0001783,"], "Ry": ["4.47e-08,"], "Rz": ["-8.565e-05"], "x_global": ["2385"], "y_global": ["1213"], "z_global": ["8512"], "average_hit_x": ["2310"], "average_hit_y": ["695.2"], "average_hit_z": ["8508"], "nTracks": ["32688"], "nHits": ["32688"], "localDeltaChi2": [607.5]}, "FT/T2/X2/HL0/Q0/M0": {"Tx": ["-0.5617,"], "Ty": ["0.0004719,"], "Tz": ["0.8922,"], "Rx": ["1.145e-05,"], "Ry": ["1.095e-07,"], "Rz": ["1.412e-05"], "x_global": ["-265"], "y_global": ["-1213"], "z_global": ["8714"], "average_hit_x": ["-244.4"], "average_hit_y": ["-392.9"], "average_hit_z": ["8719"], "nTracks": ["18550"], "nHits": ["18550"], "localDeltaChi2": [499650.0]}, "FT/T2/X2/HL0/Q0/M1": {"Tx": ["0.4668,"], "Ty": ["-0.0002461,"], "Tz": ["1.293,"], "Rx": ["0.0003767,"], "Ry": ["2.533e-07,"], "Rz": ["-2.469e-05"], "x_global": ["-795"], "y_global": ["-1213"], "z_global": ["8714"], "average_hit_x": ["-786.4"], "average_hit_y": ["-434.3"], "average_hit_z": ["8719"], "nTracks": ["511112"], "nHits": ["511112"], "localDeltaChi2": [5010.0]}, "FT/T2/X2/HL0/Q0/M2": {"Tx": ["0.5226,"], "Ty": ["-0.000226,"], "Tz": ["1.49,"], "Rx": ["0.0003584,"], "Ry": ["2.537e-07,"], "Rz": ["6.077e-05"], "x_global": ["-1325"], "y_global": ["-1213"], "z_global": ["8714"], "average_hit_x": ["-1281"], "average_hit_y": ["-539.6"], "average_hit_z": ["8719"], "nTracks": ["268688"], "nHits": ["268688"], "localDeltaChi2": [5150.0]}, "FT/T2/X2/HL0/Q0/M3": {"Tx": ["1.023,"], "Ty": ["0.0002238,"], "Tz": ["1.446,"], "Rx": ["7.641e-05,"], "Ry": ["7.242e-08,"], "Rz": ["-9.007e-05"], "x_global": ["-1855"], "y_global": ["-1213"], "z_global": ["8714"], "average_hit_x": ["-1804"], "average_hit_y": ["-711.5"], "average_hit_z": ["8719"], "nTracks": ["76667"], "nHits": ["76667"], "localDeltaChi2": [5070.0]}, "FT/T2/X2/HL0/Q0/M4": {"Tx": ["0.8819,"], "Ty": ["0.001208,"], "Tz": ["0.8159,"], "Rx": ["-0.000408,"], "Ry": ["-1.073e-07,"], "Rz": ["4.086e-06"], "x_global": ["-2385"], "y_global": ["-1213"], "z_global": ["8714"], "average_hit_x": ["-2342"], "average_hit_y": ["-701.7"], "average_hit_z": ["8720"], "nTracks": ["40843"], "nHits": ["40843"], "localDeltaChi2": [4881.0]}, "FT/T2/X2/HL0/Q2/M0": {"Tx": ["0.7624,"], "Ty": ["-0.0007823,"], "Tz": ["1.287,"], "Rx": ["0.0003373,"], "Ry": ["-3.589e-07,"], "Rz": ["-0.0001795"], "x_global": ["-265"], "y_global": ["1213"], "z_global": ["8722"], "average_hit_x": ["-219.3"], "average_hit_y": ["382.8"], "average_hit_z": ["8719"], "nTracks": ["14321"], "nHits": ["14321"], "localDeltaChi2": [499550.0]}, "FT/T2/X2/HL0/Q2/M1": {"Tx": ["-1.176,"], "Ty": ["-0.001163,"], "Tz": ["1.71,"], "Rx": ["0.0007245,"], "Ry": ["8.268e-07,"], "Rz": ["0.0006096"], "x_global": ["-795"], "y_global": ["1213"], "z_global": ["8722"], "average_hit_x": ["-789.3"], "average_hit_y": ["182.7"], "average_hit_z": ["8719"], "nTracks": ["119394"], "nHits": ["119394"], "localDeltaChi2": [5005.0]}, "FT/T2/X2/HL0/Q2/M2": {"Tx": ["-0.5934,"], "Ty": ["-0.001323,"], "Tz": ["1.567,"], "Rx": ["0.0004313,"], "Ry": ["2.605e-07,"], "Rz": ["-2.407e-06"], "x_global": ["-1325"], "y_global": ["1213"], "z_global": ["8722"], "average_hit_x": ["-1293"], "average_hit_y": ["207.5"], "average_hit_z": ["8719"], "nTracks": ["97685"], "nHits": ["97685"], "localDeltaChi2": [5145.0]}, "FT/T2/X2/HL0/Q2/M3": {"Tx": ["-0.813,"], "Ty": ["-0.0006132,"], "Tz": ["1.627,"], "Rx": ["0.0002266,"], "Ry": ["-3.938e-08,"], "Rz": ["-8.337e-05"], "x_global": ["-1855"], "y_global": ["1213"], "z_global": ["8722"], "average_hit_x": ["-1820"], "average_hit_y": ["319.3"], "average_hit_z": ["8719"], "nTracks": ["37783"], "nHits": ["37783"], "localDeltaChi2": [5070.0]}, "FT/T2/X2/HL0/Q2/M4": {"Tx": ["-0.9431,"], "Ty": ["-0.0006869,"], "Tz": ["1.718,"], "Rx": ["0.0003359,"], "Ry": ["-1.232e-07,"], "Rz": ["4.637e-05"], "x_global": ["-2385"], "y_global": ["1213"], "z_global": ["8722"], "average_hit_x": ["-2498"], "average_hit_y": ["434.4"], "average_hit_z": ["8719"], "nTracks": ["6740"], "nHits": ["6740"], "localDeltaChi2": [4880.0]}, "FT/T2/X2/HL1/Q1/M0": {"Tx": ["0.4168,"], "Ty": ["0.0002164,"], "Tz": ["0.2997,"], "Rx": ["-0.0009017,"], "Ry": ["3.603e-07,"], "Rz": ["-8.451e-05"], "x_global": ["265"], "y_global": ["-1213"], "z_global": ["8714"], "average_hit_x": ["233.1"], "average_hit_y": ["-381.2"], "average_hit_z": ["8719"], "nTracks": ["443490"], "nHits": ["443490"], "localDeltaChi2": [2269.0]}, "FT/T2/X2/HL1/Q1/M1": {"Tx": ["-0.3389,"], "Ty": ["-0.000313,"], "Tz": ["-0.1365,"], "Rx": ["-0.0005142,"], "Ry": ["4.237e-07,"], "Rz": ["2.753e-05"], "x_global": ["795"], "y_global": ["-1213"], "z_global": ["8714"], "average_hit_x": ["776.9"], "average_hit_y": ["-201.4"], "average_hit_z": ["8719"], "nTracks": ["171909"], "nHits": ["171909"], "localDeltaChi2": [445.5]}, "FT/T2/X2/HL1/Q1/M2": {"Tx": ["-0.03518,"], "Ty": ["3.866e-05,"], "Tz": ["0.04228,"], "Rx": ["-0.0003227,"], "Ry": ["1.284e-07,"], "Rz": ["-5.749e-05"], "x_global": ["1325"], "y_global": ["-1213"], "z_global": ["8714"], "average_hit_x": ["1294"], "average_hit_y": ["-209.2"], "average_hit_z": ["8718"], "nTracks": ["97912"], "nHits": ["97912"], "localDeltaChi2": [541.0]}, "FT/T2/X2/HL1/Q1/M3": {"Tx": ["0.04586,"], "Ty": ["3.165e-05,"], "Tz": ["0.08288,"], "Rx": ["5.861e-05,"], "Ry": ["7.802e-08,"], "Rz": ["-0.0002766"], "x_global": ["1855"], "y_global": ["-1213"], "z_global": ["8714"], "average_hit_x": ["1831"], "average_hit_y": ["-320.2"], "average_hit_z": ["8718"], "nTracks": ["39140"], "nHits": ["39140"], "localDeltaChi2": [120.2]}, "FT/T2/X2/HL1/Q1/M4": {"Tx": ["-0.4809,"], "Ty": ["-0.0002185,"], "Tz": ["-0.2994,"], "Rx": ["0.0001083,"], "Ry": ["-4.864e-08,"], "Rz": ["0.0001619"], "x_global": ["2385"], "y_global": ["-1213"], "z_global": ["8714"], "average_hit_x": ["2347"], "average_hit_y": ["-460.6"], "average_hit_z": ["8718"], "nTracks": ["16109"], "nHits": ["16109"], "localDeltaChi2": [1496.0]}, "FT/T2/X2/HL1/Q3/M0": {"Tx": ["-0.0003774,"], "Ty": ["0.0001953,"], "Tz": ["0.01395,"], "Rx": ["-0.001139,"], "Ry": ["3.196e-07,"], "Rz": ["-0.0002589"], "x_global": ["265"], "y_global": ["1213"], "z_global": ["8722"], "average_hit_x": ["253.7"], "average_hit_y": ["385.7"], "average_hit_z": ["8719"], "nTracks": ["599476"], "nHits": ["599476"], "localDeltaChi2": [2285.0]}, "FT/T2/X2/HL1/Q3/M1": {"Tx": ["0.311,"], "Ty": ["0.0003049,"], "Tz": ["-0.1724,"], "Rx": ["-0.0005545,"], "Ry": ["-4.205e-08,"], "Rz": ["-4.602e-06"], "x_global": ["795"], "y_global": ["1213"], "z_global": ["8722"], "average_hit_x": ["780.1"], "average_hit_y": ["417.1"], "average_hit_z": ["8718"], "nTracks": ["452686"], "nHits": ["452686"], "localDeltaChi2": [459.9]}, "FT/T2/X2/HL1/Q3/M2": {"Tx": ["0.06181,"], "Ty": ["0.0004972,"], "Tz": ["0.1557,"], "Rx": ["-0.0002388,"], "Ry": ["5.305e-08,"], "Rz": ["3.551e-05"], "x_global": ["1325"], "y_global": ["1213"], "z_global": ["8722"], "average_hit_x": ["1300"], "average_hit_y": ["532"], "average_hit_z": ["8718"], "nTracks": ["241292"], "nHits": ["241292"], "localDeltaChi2": [551.0]}, "FT/T2/X2/HL1/Q3/M3": {"Tx": ["0.1581,"], "Ty": ["0.0002925,"], "Tz": ["-0.3018,"], "Rx": ["-0.0002601,"], "Ry": ["3.952e-08,"], "Rz": ["0.0001084"], "x_global": ["1855"], "y_global": ["1213"], "z_global": ["8722"], "average_hit_x": ["1818"], "average_hit_y": ["697.2"], "average_hit_z": ["8718"], "nTracks": ["98141"], "nHits": ["98141"], "localDeltaChi2": [125.85]}, "FT/T2/X2/HL1/Q3/M4": {"Tx": ["0.2124,"], "Ty": ["0.0005715,"], "Tz": ["0.01243,"], "Rx": ["0.0003608,"], "Ry": ["-2.717e-07,"], "Rz": ["5.947e-05"], "x_global": ["2385"], "y_global": ["1213"], "z_global": ["8722"], "average_hit_x": ["2343"], "average_hit_y": ["723.2"], "average_hit_z": ["8718"], "nTracks": ["40505"], "nHits": ["40505"], "localDeltaChi2": [1498.0]}, "FT/T3/U/HL0/Q0/M0": {"Tx": ["-0.3666,"], "Ty": ["0.0001121,"], "Tz": ["0.01328,"], "Rx": ["-0.0001082,"], "Ry": ["6.272e-07,"], "Rz": ["3.764e-05"], "x_global": ["-371.7"], "y_global": ["-1208"], "z_global": ["9259"], "average_hit_x": ["-282.5"], "average_hit_y": ["-404.7"], "average_hit_z": ["9264"], "nTracks": ["377154"], "nHits": ["377154"], "localDeltaChi2": [1135.5]}, "FT/T3/U/HL0/Q0/M1": {"Tx": ["-0.249,"], "Ty": ["-0.0004495,"], "Tz": ["0.5464,"], "Rx": ["0.0005998,"], "Ry": ["-8.739e-08,"], "Rz": ["0.000163"], "x_global": ["-903.7"], "y_global": ["-1208"], "z_global": ["9259"], "average_hit_x": ["-835.2"], "average_hit_y": ["-456.8"], "average_hit_z": ["9263"], "nTracks": ["461809"], "nHits": ["461809"], "localDeltaChi2": [14870.0]}, "FT/T3/U/HL0/Q0/M2": {"Tx": ["-0.005301,"], "Ty": ["-0.0002628,"], "Tz": ["0.4585,"], "Rx": ["0.0002853,"], "Ry": ["1.678e-07,"], "Rz": ["-7.453e-05"], "x_global": ["-1436"], "y_global": ["-1208"], "z_global": ["9259"], "average_hit_x": ["-1342"], "average_hit_y": ["-555.4"], "average_hit_z": ["9263"], "nTracks": ["281125"], "nHits": ["281125"], "localDeltaChi2": [9105.0]}, "FT/T3/U/HL0/Q0/M3": {"Tx": ["0.1558,"], "Ty": ["6.971e-05,"], "Tz": ["0.2932,"], "Rx": ["-2.547e-05,"], "Ry": ["1.337e-07,"], "Rz": ["0.0001594"], "x_global": ["-1968"], "y_global": ["-1208"], "z_global": ["9259"], "average_hit_x": ["-1863"], "average_hit_y": ["-677.9"], "average_hit_z": ["9264"], "nTracks": ["87567"], "nHits": ["87567"], "localDeltaChi2": [8055.0]}, "FT/T3/U/HL0/Q0/M4": {"Tx": ["-0.03815,"], "Ty": ["0.0003018,"], "Tz": ["0.6372,"], "Rx": ["-0.0003183,"], "Ry": ["1.687e-07,"], "Rz": ["0.0001963"], "x_global": ["-2500"], "y_global": ["-1208"], "z_global": ["9259"], "average_hit_x": ["-2436"], "average_hit_y": ["-754.9"], "average_hit_z": ["9264"], "nTracks": ["42839"], "nHits": ["42839"], "localDeltaChi2": [7890.0]}, "FT/T3/U/HL0/Q0/M5": {"Tx": ["-0.6602,"], "Ty": ["0.001742,"], "Tz": ["0.06654,"], "Rx": ["-9.758e-05,"], "Ry": ["-9.249e-09,"], "Rz": ["0.0002745"], "x_global": ["-3032"], "y_global": ["-1208"], "z_global": ["9259"], "average_hit_x": ["-2795"], "average_hit_y": ["-524.1"], "average_hit_z": ["9264"], "nTracks": ["7290"], "nHits": ["7290"], "localDeltaChi2": [6440.0]}, "FT/T3/U/HL0/Q2/M0": {"Tx": ["0.2812,"], "Ty": ["-0.001892,"], "Tz": ["1.14,"], "Rx": ["0.0008174,"], "Ry": ["-7.493e-07,"], "Rz": ["3.285e-05"], "x_global": ["-160.3"], "y_global": ["1208"], "z_global": ["9267"], "average_hit_x": ["-174.8"], "average_hit_y": ["470.6"], "average_hit_z": ["9263"], "nTracks": ["289362"], "nHits": ["289362"], "localDeltaChi2": [1141.5]}, "FT/T3/U/HL0/Q2/M1": {"Tx": ["-0.3918,"], "Ty": ["-0.001605,"], "Tz": ["0.9039,"], "Rx": ["0.0008986,"], "Ry": ["4.042e-07,"], "Rz": ["0.0003654"], "x_global": ["-692.3"], "y_global": ["1208"], "z_global": ["9267"], "average_hit_x": ["-789.3"], "average_hit_y": ["223"], "average_hit_z": ["9263"], "nTracks": ["125805"], "nHits": ["125805"], "localDeltaChi2": [14865.0]}, "FT/T3/U/HL0/Q2/M2": {"Tx": ["-0.2137,"], "Ty": ["-0.001862,"], "Tz": ["1.256,"], "Rx": ["0.000945,"], "Ry": ["6.485e-07,"], "Rz": ["0.0002551"], "x_global": ["-1224"], "y_global": ["1208"], "z_global": ["9267"], "average_hit_x": ["-1292"], "average_hit_y": ["204.1"], "average_hit_z": ["9263"], "nTracks": ["102226"], "nHits": ["102226"], "localDeltaChi2": [9100.0]}, "FT/T3/U/HL0/Q2/M3": {"Tx": ["-0.204,"], "Ty": ["-0.002958,"], "Tz": ["1.662,"], "Rx": ["0.001104,"], "Ry": ["1.152e-06,"], "Rz": ["-0.0001197"], "x_global": ["-1756"], "y_global": ["1208"], "z_global": ["9267"], "average_hit_x": ["-1798"], "average_hit_y": ["280.9"], "average_hit_z": ["9264"], "nTracks": ["48206"], "nHits": ["48206"], "localDeltaChi2": [8050.0]}, "FT/T3/U/HL0/Q2/M4": {"Tx": ["-0.2609,"], "Ty": ["-0.004838,"], "Tz": ["2.351,"], "Rx": ["0.001096,"], "Ry": ["8.24e-07,"], "Rz": ["5.027e-05"], "x_global": ["-2288"], "y_global": ["1208"], "z_global": ["9267"], "average_hit_x": ["-2308"], "average_hit_y": ["391.7"], "average_hit_z": ["9264"], "nTracks": ["19248"], "nHits": ["19248"], "localDeltaChi2": [7885.0]}, "FT/T3/U/HL0/Q2/M5": {"Tx": ["1.458,"], "Ty": ["-0.002853,"], "Tz": ["0.1357,"], "Rx": ["-4.083e-05,"], "Ry": ["-5e-07,"], "Rz": ["-0.000932"], "x_global": ["-2820"], "y_global": ["1208"], "z_global": ["9267"], "average_hit_x": ["-2735"], "average_hit_y": ["488.8"], "average_hit_z": ["9264"], "nTracks": ["5939"], "nHits": ["5939"], "localDeltaChi2": [6440.0]}, "FT/T3/U/HL1/Q1/M0": {"Tx": ["-0.1212,"], "Ty": ["0.0001663,"], "Tz": ["-0.002541,"], "Rx": ["0.0004781,"], "Ry": ["1.586e-08,"], "Rz": ["-0.0002155"], "x_global": ["160.3"], "y_global": ["-1208"], "z_global": ["9259"], "average_hit_x": ["220.1"], "average_hit_y": ["-417.1"], "average_hit_z": ["9263"], "nTracks": ["432287"], "nHits": ["432287"], "localDeltaChi2": [3512.0]}, "FT/T3/U/HL1/Q1/M1": {"Tx": ["-0.8393,"], "Ty": ["-0.00174,"], "Tz": ["1.404,"], "Rx": ["0.0004526,"], "Ry": ["3.048e-08,"], "Rz": ["0.0001461"], "x_global": ["692.3"], "y_global": ["-1208"], "z_global": ["9259"], "average_hit_x": ["743.8"], "average_hit_y": ["-278.8"], "average_hit_z": ["9264"], "nTracks": ["184147"], "nHits": ["184147"], "localDeltaChi2": [175.1]}, "FT/T3/U/HL1/Q1/M2": {"Tx": ["-0.1653,"], "Ty": ["0.0001233,"], "Tz": ["0.1019,"], "Rx": ["-7.969e-05,"], "Ry": ["5.433e-08,"], "Rz": ["-0.0002068"], "x_global": ["1224"], "y_global": ["-1208"], "z_global": ["9259"], "average_hit_x": ["1289"], "average_hit_y": ["-205.4"], "average_hit_z": ["9264"], "nTracks": ["98616"], "nHits": ["98616"], "localDeltaChi2": [32.155]}, "FT/T3/U/HL1/Q1/M3": {"Tx": ["-0.3856,"], "Ty": ["-0.001389,"], "Tz": ["1.221,"], "Rx": ["0.0004529,"], "Ry": ["9.709e-09,"], "Rz": ["-0.0002113"], "x_global": ["1756"], "y_global": ["-1208"], "z_global": ["9259"], "average_hit_x": ["1791"], "average_hit_y": ["-285.1"], "average_hit_z": ["9264"], "nTracks": ["44581"], "nHits": ["44581"], "localDeltaChi2": [5.35]}, "FT/T3/U/HL1/Q1/M4": {"Tx": ["-0.09327,"], "Ty": ["-0.0003017,"], "Tz": ["0.6093,"], "Rx": ["-9.262e-06,"], "Ry": ["-5.265e-08,"], "Rz": ["-0.0003411"], "x_global": ["2288"], "y_global": ["-1208"], "z_global": ["9259"], "average_hit_x": ["2337"], "average_hit_y": ["-409.3"], "average_hit_z": ["9264"], "nTracks": ["22908"], "nHits": ["22908"], "localDeltaChi2": [44.24]}, "FT/T3/U/HL1/Q1/M5": {"Tx": ["0.1583,"], "Ty": ["-0.001695,"], "Tz": ["-0.9676,"], "Rx": ["-0.0008106,"], "Ry": ["-3.26e-08,"], "Rz": ["-0.0007839"], "x_global": ["2820"], "y_global": ["-1208"], "z_global": ["9259"], "average_hit_x": ["2754"], "average_hit_y": ["-484.1"], "average_hit_z": ["9264"], "nTracks": ["7896"], "nHits": ["7896"], "localDeltaChi2": [82.5]}, "FT/T3/U/HL1/Q3/M0": {"Tx": ["0.7703,"], "Ty": ["-0.0005225,"], "Tz": ["-1.145,"], "Rx": ["-0.000466,"], "Ry": ["1.35e-07,"], "Rz": ["-0.0003198"], "x_global": ["371.7"], "y_global": ["1208"], "z_global": ["9267"], "average_hit_x": ["287.3"], "average_hit_y": ["399.8"], "average_hit_z": ["9264"], "nTracks": ["529087"], "nHits": ["529087"], "localDeltaChi2": [3522.5]}, "FT/T3/U/HL1/Q3/M1": {"Tx": ["0.2914,"], "Ty": ["0.001034,"], "Tz": ["0.3874,"], "Rx": ["-0.0003864,"], "Ry": ["2.326e-07,"], "Rz": ["0.0003056"], "x_global": ["903.7"], "y_global": ["1208"], "z_global": ["9267"], "average_hit_x": ["829.2"], "average_hit_y": ["440.5"], "average_hit_z": ["9264"], "nTracks": ["419487"], "nHits": ["419487"], "localDeltaChi2": [186.7]}, "FT/T3/U/HL1/Q3/M2": {"Tx": ["0.4031,"], "Ty": ["0.0006507,"], "Tz": ["0.1402,"], "Rx": ["-4.683e-05,"], "Ry": ["-2.552e-08,"], "Rz": ["1.07e-05"], "x_global": ["1436"], "y_global": ["1208"], "z_global": ["9267"], "average_hit_x": ["1500"], "average_hit_y": ["579.9"], "average_hit_z": ["9264"], "nTracks": ["114516"], "nHits": ["114516"], "localDeltaChi2": [37.685]}, "FT/T3/U/HL1/Q3/M3": {"Tx": ["0.6161,"], "Ty": ["0.0005924,"], "Tz": ["0.8203,"], "Rx": ["0.0001231,"], "Ry": ["-2.957e-09,"], "Rz": ["2.125e-05"], "x_global": ["1968"], "y_global": ["1208"], "z_global": ["9267"], "average_hit_x": ["1885"], "average_hit_y": ["696.1"], "average_hit_z": ["9264"], "nTracks": ["105436"], "nHits": ["105436"], "localDeltaChi2": [12.195]}, "FT/T3/U/HL1/Q3/M4": {"Tx": ["0.5915,"], "Ty": ["0.0001914,"], "Tz": ["1.045,"], "Rx": ["0.0003483,"], "Ry": ["-3.032e-07,"], "Rz": ["-6.969e-05"], "x_global": ["2500"], "y_global": ["1208"], "z_global": ["9267"], "average_hit_x": ["2425"], "average_hit_y": ["737.6"], "average_hit_z": ["9264"], "nTracks": ["45734"], "nHits": ["45734"], "localDeltaChi2": [47.37]}, "FT/T3/U/HL1/Q3/M5": {"Tx": ["0.6053,"], "Ty": ["-0.001132,"], "Tz": ["1.111,"], "Rx": ["0.0009031,"], "Ry": ["-1.134e-06,"], "Rz": ["0.0001542"], "x_global": ["3032"], "y_global": ["1208"], "z_global": ["9267"], "average_hit_x": ["2794"], "average_hit_y": ["547.9"], "average_hit_z": ["9263"], "nTracks": ["7221"], "nHits": ["7221"], "localDeltaChi2": [82.65]}, "FT/T3/V/HL0/Q0/M0": {"Tx": ["-0.6034,"], "Ty": ["-0.003885,"], "Tz": ["2.599,"], "Rx": ["0.0004983,"], "Ry": ["3.457e-07,"], "Rz": ["8.394e-05"], "x_global": ["-160.3"], "y_global": ["-1208"], "z_global": ["9329"], "average_hit_x": ["-217.4"], "average_hit_y": ["-405.4"], "average_hit_z": ["9331"], "nTracks": ["381660"], "nHits": ["381660"], "localDeltaChi2": [2446.5]}, "FT/T3/V/HL0/Q0/M1": {"Tx": ["-0.4762,"], "Ty": ["-0.005319,"], "Tz": ["3.45,"], "Rx": ["0.0006132,"], "Ry": ["-5.826e-07,"], "Rz": ["3.235e-06"], "x_global": ["-692.3"], "y_global": ["-1208"], "z_global": ["9329"], "average_hit_x": ["-771.5"], "average_hit_y": ["-439.5"], "average_hit_z": ["9331"], "nTracks": ["421189"], "nHits": ["421189"], "localDeltaChi2": [10245.0]}, "FT/T3/V/HL0/Q0/M2": {"Tx": ["0.1396,"], "Ty": ["-0.003811,"], "Tz": ["3.154,"], "Rx": ["0.0005321,"], "Ry": ["-2.643e-07,"], "Rz": ["-0.0005642"], "x_global": ["-1224"], "y_global": ["-1208"], "z_global": ["9329"], "average_hit_x": ["-1256"], "average_hit_y": ["-539"], "average_hit_z": ["9331"], "nTracks": ["312071"], "nHits": ["312071"], "localDeltaChi2": [8190.0]}, "FT/T3/V/HL0/Q0/M3": {"Tx": ["-0.2826,"], "Ty": ["-0.0002075,"], "Tz": ["1.826,"], "Rx": ["-0.0001852,"], "Ry": ["9.02e-09,"], "Rz": ["-0.0004364"], "x_global": ["-1756"], "y_global": ["-1208"], "z_global": ["9329"], "average_hit_x": ["-1742"], "average_hit_y": ["-739.6"], "average_hit_z": ["9331"], "nTracks": ["114866"], "nHits": ["114866"], "localDeltaChi2": [7910.0]}, "FT/T3/V/HL0/Q0/M4": {"Tx": ["-0.2502,"], "Ty": ["-0.0009483,"], "Tz": ["2.253,"], "Rx": ["0.0001077,"], "Ry": ["-1.621e-07,"], "Rz": ["-0.0004884"], "x_global": ["-2288"], "y_global": ["-1208"], "z_global": ["9329"], "average_hit_x": ["-2322"], "average_hit_y": ["-805"], "average_hit_z": ["9331"], "nTracks": ["46042"], "nHits": ["46042"], "localDeltaChi2": [7300.0]}, "FT/T3/V/HL0/Q0/M5": {"Tx": ["-0.7256,"], "Ty": ["0.0008147,"], "Tz": ["1.921,"], "Rx": ["-0.0005146,"], "Ry": ["2.166e-07,"], "Rz": ["-9.407e-05"], "x_global": ["-2820"], "y_global": ["-1208"], "z_global": ["9329"], "average_hit_x": ["-2735"], "average_hit_y": ["-839.6"], "average_hit_z": ["9331"], "nTracks": ["16312"], "nHits": ["16312"], "localDeltaChi2": [8000.0]}, "FT/T3/V/HL0/Q2/M0": {"Tx": ["0.3085,"], "Ty": ["-0.00693,"], "Tz": ["3.155,"], "Rx": ["0.0009557,"], "Ry": ["1.035e-07,"], "Rz": ["0.0001592"], "x_global": ["-371.7"], "y_global": ["1208"], "z_global": ["9337"], "average_hit_x": ["-251"], "average_hit_y": ["413.8"], "average_hit_z": ["9332"], "nTracks": ["228137"], "nHits": ["228137"], "localDeltaChi2": [2449.5]}, "FT/T3/V/HL0/Q2/M1": {"Tx": ["-0.4042,"], "Ty": ["-0.002206,"], "Tz": ["3.023,"], "Rx": ["0.0002617,"], "Ry": ["3.978e-07,"], "Rz": ["0.0007227"], "x_global": ["-903.7"], "y_global": ["1208"], "z_global": ["9337"], "average_hit_x": ["-831.5"], "average_hit_y": ["200.9"], "average_hit_z": ["9331"], "nTracks": ["125517"], "nHits": ["125517"], "localDeltaChi2": [10240.0]}, "FT/T3/V/HL0/Q2/M2": {"Tx": ["0.4034,"], "Ty": ["0.0008191,"], "Tz": ["1.415,"], "Rx": ["-0.0009013,"], "Ry": ["-7.279e-07,"], "Rz": ["0.0001165"], "x_global": ["-1436"], "y_global": ["1208"], "z_global": ["9337"], "average_hit_x": ["-1329"], "average_hit_y": ["209.2"], "average_hit_z": ["9330"], "nTracks": ["99835"], "nHits": ["99835"], "localDeltaChi2": [8185.0]}, "FT/T3/V/HL0/Q2/M3": {"Tx": ["0.2608,"], "Ty": ["0.0004528,"], "Tz": ["1.647,"], "Rx": ["-0.0003299,"], "Ry": ["-3.194e-07,"], "Rz": ["0.0004544"], "x_global": ["-1968"], "y_global": ["1208"], "z_global": ["9337"], "average_hit_x": ["-1855"], "average_hit_y": ["287.7"], "average_hit_z": ["9331"], "nTracks": ["46038"], "nHits": ["46038"], "localDeltaChi2": [7910.0]}, "FT/T3/V/HL0/Q2/M4": {"Tx": ["0.6914,"], "Ty": ["0.002154,"], "Tz": ["1.292,"], "Rx": ["-0.0006838,"], "Ry": ["-4.221e-07,"], "Rz": ["0.0001246"], "x_global": ["-2500"], "y_global": ["1208"], "z_global": ["9337"], "average_hit_x": ["-2388"], "average_hit_y": ["400.9"], "average_hit_z": ["9331"], "nTracks": ["18225"], "nHits": ["18225"], "localDeltaChi2": [7300.0]}, "FT/T3/V/HL0/Q2/M5": {"Tx": ["-0.4699,"], "Ty": ["0.004029,"], "Tz": ["2.174,"], "Rx": ["-0.0003051,"], "Ry": ["-3.354e-08,"], "Rz": ["0.00108"], "x_global": ["-3032"], "y_global": ["1208"], "z_global": ["9337"], "average_hit_x": ["-2797"], "average_hit_y": ["421.2"], "average_hit_z": ["9331"], "nTracks": ["4265"], "nHits": ["4265"], "localDeltaChi2": [8000.0]}, "FT/T3/V/HL1/Q1/M0": {"Tx": ["-0.1141,"], "Ty": ["-0.0004629,"], "Tz": ["0.2689,"], "Rx": ["0.00067,"], "Ry": ["2.798e-07,"], "Rz": ["-4.309e-05"], "x_global": ["371.7"], "y_global": ["-1208"], "z_global": ["9329"], "average_hit_x": ["273.4"], "average_hit_y": ["-397.7"], "average_hit_z": ["9334"], "nTracks": ["411857"], "nHits": ["411857"], "localDeltaChi2": [3277.0]}, "FT/T3/V/HL1/Q1/M1": {"Tx": ["-0.1037,"], "Ty": ["1.765e-06,"], "Tz": ["0.008252,"], "Rx": ["0.0005767,"], "Ry": ["7.761e-07,"], "Rz": ["0.0002706"], "x_global": ["903.7"], "y_global": ["-1208"], "z_global": ["9329"], "average_hit_x": ["795.3"], "average_hit_y": ["-236.2"], "average_hit_z": ["9333"], "nTracks": ["168618"], "nHits": ["168618"], "localDeltaChi2": [774.0]}, "FT/T3/V/HL1/Q1/M2": {"Tx": ["0.01952,"], "Ty": ["0.0006937,"], "Tz": ["-0.2044,"], "Rx": ["0.0001202,"], "Ry": ["8.846e-08,"], "Rz": ["0.0002822"], "x_global": ["1436"], "y_global": ["-1208"], "z_global": ["9329"], "average_hit_x": ["1330"], "average_hit_y": ["-204.3"], "average_hit_z": ["9333"], "nTracks": ["101127"], "nHits": ["101127"], "localDeltaChi2": [305.65]}, "FT/T3/V/HL1/Q1/M3": {"Tx": ["0.3892,"], "Ty": ["0.0009788,"], "Tz": ["-0.1143,"], "Rx": ["0.0006317,"], "Ry": ["7.166e-07,"], "Rz": ["0.0002725"], "x_global": ["1968"], "y_global": ["-1208"], "z_global": ["9329"], "average_hit_x": ["1852"], "average_hit_y": ["-292.4"], "average_hit_z": ["9334"], "nTracks": ["44722"], "nHits": ["44722"], "localDeltaChi2": [65.25]}, "FT/T3/V/HL1/Q1/M4": {"Tx": ["0.5458,"], "Ty": ["-0.001239,"], "Tz": ["-1.072,"], "Rx": ["-0.0009357,"], "Ry": ["-8.51e-07,"], "Rz": ["-0.000243"], "x_global": ["2500"], "y_global": ["-1208"], "z_global": ["9329"], "average_hit_x": ["2410"], "average_hit_y": ["-408.7"], "average_hit_z": ["9333"], "nTracks": ["23440"], "nHits": ["23440"], "localDeltaChi2": [43.715]}, "FT/T3/V/HL1/Q1/M5": {"Tx": ["-1.2,"], "Ty": ["-0.00362,"], "Tz": ["2.275,"], "Rx": ["0.0008045,"], "Ry": ["4.62e-07,"], "Rz": ["0.001159"], "x_global": ["3032"], "y_global": ["-1208"], "z_global": ["9329"], "average_hit_x": ["2815"], "average_hit_y": ["-431.8"], "average_hit_z": ["9332"], "nTracks": ["6067"], "nHits": ["6067"], "localDeltaChi2": [955.5]}, "FT/T3/V/HL1/Q3/M0": {"Tx": ["0.104,"], "Ty": ["-0.00307,"], "Tz": ["1.07,"], "Rx": ["0.001328,"], "Ry": ["8.061e-07,"], "Rz": ["5.138e-05"], "x_global": ["160.3"], "y_global": ["1208"], "z_global": ["9337"], "average_hit_x": ["219.8"], "average_hit_y": ["416.9"], "average_hit_z": ["9334"], "nTracks": ["538120"], "nHits": ["538120"], "localDeltaChi2": [3288.5]}, "FT/T3/V/HL1/Q3/M1": {"Tx": ["-0.3861,"], "Ty": ["-0.001578,"], "Tz": ["0.7046,"], "Rx": ["0.001147,"], "Ry": ["2.992e-07,"], "Rz": ["0.0001332"], "x_global": ["692.3"], "y_global": ["1208"], "z_global": ["9337"], "average_hit_x": ["635.4"], "average_hit_y": ["411.8"], "average_hit_z": ["9334"], "nTracks": ["227485"], "nHits": ["227485"], "localDeltaChi2": [780.0]}, "FT/T3/V/HL1/Q3/M2": {"Tx": ["-0.1092,"], "Ty": ["-0.002103,"], "Tz": ["0.9758,"], "Rx": ["0.001088,"], "Ry": ["5.277e-07,"], "Rz": ["-0.0002083"], "x_global": ["1224"], "y_global": ["1208"], "z_global": ["9337"], "average_hit_x": ["1256"], "average_hit_y": ["524.1"], "average_hit_z": ["9334"], "nTracks": ["274596"], "nHits": ["274596"], "localDeltaChi2": [314.55]}, "FT/T3/V/HL1/Q3/M3": {"Tx": ["-0.4373,"], "Ty": ["0.0002586,"], "Tz": ["0.1698,"], "Rx": ["0.0008663,"], "Ry": ["4.366e-08,"], "Rz": ["-0.0002328"], "x_global": ["1756"], "y_global": ["1208"], "z_global": ["9337"], "average_hit_x": ["1757"], "average_hit_y": ["707.7"], "average_hit_z": ["9334"], "nTracks": ["131680"], "nHits": ["131680"], "localDeltaChi2": [70.95]}, "FT/T3/V/HL1/Q3/M4": {"Tx": ["-0.1338,"], "Ty": ["-0.001537,"], "Tz": ["1.112,"], "Rx": ["0.0008661,"], "Ry": ["3.293e-07,"], "Rz": ["-9.671e-05"], "x_global": ["2288"], "y_global": ["1208"], "z_global": ["9337"], "average_hit_x": ["2287"], "average_hit_y": ["819.1"], "average_hit_z": ["9334"], "nTracks": ["58977"], "nHits": ["58977"], "localDeltaChi2": [46.645]}, "FT/T3/V/HL1/Q3/M5": {"Tx": ["-1.009,"], "Ty": ["-0.001115,"], "Tz": ["-0.1933,"], "Rx": ["-0.001231,"], "Ry": ["-9.457e-07,"], "Rz": ["0.0006623"], "x_global": ["2820"], "y_global": ["1208"], "z_global": ["9337"], "average_hit_x": ["2733"], "average_hit_y": ["868.4"], "average_hit_z": ["9332"], "nTracks": ["18093"], "nHits": ["18093"], "localDeltaChi2": [956.5]}, "FT/T3/X1/HL0/Q0/M0": {"Tx": ["-0.1044,"], "Ty": ["4.303e-05,"], "Tz": ["0.1403,"], "Rx": ["-0.00135,"], "Ry": ["1.482e-06,"], "Rz": ["2.694e-05"], "x_global": ["-265"], "y_global": ["-1213"], "z_global": ["9189"], "average_hit_x": ["-248.9"], "average_hit_y": ["-393.3"], "average_hit_z": ["9191"], "nTracks": ["379213"], "nHits": ["379213"], "localDeltaChi2": [1299.0]}, "FT/T3/X1/HL0/Q0/M1": {"Tx": ["-0.3036,"], "Ty": ["0.0009067,"], "Tz": ["0.7594,"], "Rx": ["-0.000797,"], "Ry": ["4.391e-07,"], "Rz": ["6.136e-05"], "x_global": ["-795"], "y_global": ["-1213"], "z_global": ["9189"], "average_hit_x": ["-798.7"], "average_hit_y": ["-443.8"], "average_hit_z": ["9192"], "nTracks": ["458201"], "nHits": ["458201"], "localDeltaChi2": [13515.0]}, "FT/T3/X1/HL0/Q0/M2": {"Tx": ["-0.7386,"], "Ty": ["-0.003522,"], "Tz": ["-1.273,"], "Rx": ["-0.001159,"], "Ry": ["1.555e-07,"], "Rz": ["0.0001284"], "x_global": ["-1325"], "y_global": ["-1213"], "z_global": ["9189"], "average_hit_x": ["-1285"], "average_hit_y": ["-554"], "average_hit_z": ["9192"], "nTracks": ["292496"], "nHits": ["292496"], "localDeltaChi2": [8800.0]}, "FT/T3/X1/HL0/Q0/M3": {"Tx": ["-0.4103,"], "Ty": ["-0.0003178,"], "Tz": ["0.000453,"], "Rx": ["-0.0006094,"], "Ry": ["2.936e-07,"], "Rz": ["5.742e-06"], "x_global": ["-1855"], "y_global": ["-1213"], "z_global": ["9189"], "average_hit_x": ["-1802"], "average_hit_y": ["-706.1"], "average_hit_z": ["9193"], "nTracks": ["87100"], "nHits": ["87100"], "localDeltaChi2": [7515.0]}, "FT/T3/X1/HL0/Q0/M4": {"Tx": ["-0.8996,"], "Ty": ["-0.001176,"], "Tz": ["-0.3267,"], "Rx": ["-0.000392,"], "Ry": ["5.823e-07,"], "Rz": ["0.0001076"], "x_global": ["-2385"], "y_global": ["-1213"], "z_global": ["9189"], "average_hit_x": ["-2366"], "average_hit_y": ["-771.6"], "average_hit_z": ["9193"], "nTracks": ["46150"], "nHits": ["46150"], "localDeltaChi2": [8460.0]}, "FT/T3/X1/HL0/Q0/M5": {"Tx": ["-0.9882,"], "Ty": ["-0.001516,"], "Tz": ["-0.69,"], "Rx": ["-0.0001575,"], "Ry": ["3.331e-07,"], "Rz": ["0.0002197"], "x_global": ["-2915"], "y_global": ["-1213"], "z_global": ["9189"], "average_hit_x": ["-2746"], "average_hit_y": ["-627.3"], "average_hit_z": ["9194"], "nTracks": ["9653"], "nHits": ["9653"], "localDeltaChi2": [8465.0]}, "FT/T3/X1/HL0/Q2/M0": {"Tx": ["-0.2009,"], "Ty": ["-0.001633,"], "Tz": ["2.196,"], "Rx": ["0.0003361,"], "Ry": ["1.537e-07,"], "Rz": ["0.0002248"], "x_global": ["-265"], "y_global": ["1213"], "z_global": ["9197"], "average_hit_x": ["-215.9"], "average_hit_y": ["440.4"], "average_hit_z": ["9194"], "nTracks": ["246701"], "nHits": ["246701"], "localDeltaChi2": [1306.0]}, "FT/T3/X1/HL0/Q2/M1": {"Tx": ["-1.644,"], "Ty": ["-0.0002944,"], "Tz": ["0.5041,"], "Rx": ["-0.001001,"], "Ry": ["-8.833e-07,"], "Rz": ["0.001545"], "x_global": ["-795"], "y_global": ["1213"], "z_global": ["9197"], "average_hit_x": ["-798.2"], "average_hit_y": ["190"], "average_hit_z": ["9192"], "nTracks": ["108489"], "nHits": ["108489"], "localDeltaChi2": [13510.0]}, "FT/T3/X1/HL0/Q2/M2": {"Tx": ["-0.634,"], "Ty": ["-0.001087,"], "Tz": ["-0.7948,"], "Rx": ["-0.0007561,"], "Ry": ["6.372e-09,"], "Rz": ["0.001003"], "x_global": ["-1325"], "y_global": ["1213"], "z_global": ["9197"], "average_hit_x": ["-1299"], "average_hit_y": ["197.5"], "average_hit_z": ["9193"], "nTracks": ["96469"], "nHits": ["96469"], "localDeltaChi2": [8795.0]}, "FT/T3/X1/HL0/Q2/M3": {"Tx": ["0.298,"], "Ty": ["-0.001551,"], "Tz": ["-0.6597,"], "Rx": ["-0.001151,"], "Ry": ["-9.459e-08,"], "Rz": ["8.686e-05"], "x_global": ["-1855"], "y_global": ["1213"], "z_global": ["9197"], "average_hit_x": ["-1815"], "average_hit_y": ["286.1"], "average_hit_z": ["9193"], "nTracks": ["47719"], "nHits": ["47719"], "localDeltaChi2": [7510.0]}, "FT/T3/X1/HL0/Q2/M4": {"Tx": ["0.9775,"], "Ty": ["-0.00393,"], "Tz": ["-1.424,"], "Rx": ["-0.001297,"], "Ry": ["-4.332e-07,"], "Rz": ["-0.0001718"], "x_global": ["-2385"], "y_global": ["1213"], "z_global": ["9197"], "average_hit_x": ["-2341"], "average_hit_y": ["394.5"], "average_hit_z": ["9193"], "nTracks": ["18618"], "nHits": ["18618"], "localDeltaChi2": [8460.0]}, "FT/T3/X1/HL0/Q2/M5": {"Tx": ["0.6434,"], "Ty": ["-0.0005431,"], "Tz": ["-1.194,"], "Rx": ["-0.0005738,"], "Ry": ["-2.95e-07,"], "Rz": ["6.456e-05"], "x_global": ["-2915"], "y_global": ["1213"], "z_global": ["9197"], "average_hit_x": ["-2743"], "average_hit_y": ["449.8"], "average_hit_z": ["9194"], "nTracks": ["4280"], "nHits": ["4280"], "localDeltaChi2": [8465.0]}, "FT/T3/X1/HL1/Q1/M0": {"Tx": ["-0.2511,"], "Ty": ["-0.0001716,"], "Tz": ["0.7081,"], "Rx": ["-3.402e-05,"], "Ry": ["-1.561e-07,"], "Rz": ["0.0001271"], "x_global": ["265"], "y_global": ["-1213"], "z_global": ["9189"], "average_hit_x": ["243"], "average_hit_y": ["-399.7"], "average_hit_z": ["9193"], "nTracks": ["419678"], "nHits": ["419678"], "localDeltaChi2": [3177.0]}, "FT/T3/X1/HL1/Q1/M1": {"Tx": ["-0.1354,"], "Ty": ["-0.0004234,"], "Tz": ["-0.1723,"], "Rx": ["-0.0006153,"], "Ry": ["-6.257e-07,"], "Rz": ["0.000187"], "x_global": ["795"], "y_global": ["-1213"], "z_global": ["9189"], "average_hit_x": ["770.7"], "average_hit_y": ["-243.1"], "average_hit_z": ["9192"], "nTracks": ["173418"], "nHits": ["173418"], "localDeltaChi2": [684.5]}, "FT/T3/X1/HL1/Q1/M2": {"Tx": ["-0.5292,"], "Ty": ["-0.0006873,"], "Tz": ["-0.327,"], "Rx": ["-0.0008773,"], "Ry": ["-2.445e-07,"], "Rz": ["0.0006684"], "x_global": ["1325"], "y_global": ["-1213"], "z_global": ["9189"], "average_hit_x": ["1304"], "average_hit_y": ["-202.3"], "average_hit_z": ["9192"], "nTracks": ["103361"], "nHits": ["103361"], "localDeltaChi2": [219.85]}, "FT/T3/X1/HL1/Q1/M3": {"Tx": ["-0.03981,"], "Ty": ["-0.0003716,"], "Tz": ["-0.4086,"], "Rx": ["-0.0006369,"], "Ry": ["-5.647e-07,"], "Rz": ["0.0004145"], "x_global": ["1855"], "y_global": ["-1213"], "z_global": ["9189"], "average_hit_x": ["1819"], "average_hit_y": ["-292.5"], "average_hit_z": ["9193"], "nTracks": ["45978"], "nHits": ["45978"], "localDeltaChi2": [1.2465]}, "FT/T3/X1/HL1/Q1/M4": {"Tx": ["0.1905,"], "Ty": ["-0.001394,"], "Tz": ["-0.9037,"], "Rx": ["-0.0008402,"], "Ry": ["-3.605e-07,"], "Rz": ["0.0004147"], "x_global": ["2385"], "y_global": ["-1213"], "z_global": ["9189"], "average_hit_x": ["2362"], "average_hit_y": ["-407.2"], "average_hit_z": ["9193"], "nTracks": ["23715"], "nHits": ["23715"], "localDeltaChi2": [38.8]}, "FT/T3/X1/HL1/Q1/M5": {"Tx": ["0.1979,"], "Ty": ["0.001362,"], "Tz": ["0.3898,"], "Rx": ["-0.0003259,"], "Ry": ["-1.016e-07,"], "Rz": ["0.0006784"], "x_global": ["2915"], "y_global": ["-1213"], "z_global": ["9189"], "average_hit_x": ["2758"], "average_hit_y": ["-451.8"], "average_hit_z": ["9192"], "nTracks": ["5712"], "nHits": ["5712"], "localDeltaChi2": [825.5]}, "FT/T3/X1/HL1/Q3/M0": {"Tx": ["-0.1602,"], "Ty": ["-3.691e-05,"], "Tz": ["0.8351,"], "Rx": ["7.633e-05,"], "Ry": ["3.233e-08,"], "Rz": ["0.000212"], "x_global": ["265"], "y_global": ["1213"], "z_global": ["9197"], "average_hit_x": ["249.2"], "average_hit_y": ["409.3"], "average_hit_z": ["9193"], "nTracks": ["544911"], "nHits": ["544911"], "localDeltaChi2": [3193.5]}, "FT/T3/X1/HL1/Q3/M1": {"Tx": ["-0.4197,"], "Ty": ["0.0003421,"], "Tz": ["0.4294,"], "Rx": ["-0.000121,"], "Ry": ["-6.273e-08,"], "Rz": ["0.0002707"], "x_global": ["795"], "y_global": ["1213"], "z_global": ["9197"], "average_hit_x": ["784.3"], "average_hit_y": ["420"], "average_hit_z": ["9193"], "nTracks": ["421118"], "nHits": ["421118"], "localDeltaChi2": [700.0]}, "FT/T3/X1/HL1/Q3/M2": {"Tx": ["-0.2876,"], "Ty": ["0.0004673,"], "Tz": ["0.1411,"], "Rx": ["-0.000493,"], "Ry": ["-3.662e-07,"], "Rz": ["5.113e-06"], "x_global": ["1325"], "y_global": ["1213"], "z_global": ["9197"], "average_hit_x": ["1296"], "average_hit_y": ["543.1"], "average_hit_z": ["9192"], "nTracks": ["244297"], "nHits": ["244297"], "localDeltaChi2": [233.1]}, "FT/T3/X1/HL1/Q3/M3": {"Tx": ["-0.829,"], "Ty": ["0.0001134,"], "Tz": ["-0.3135,"], "Rx": ["-0.0005609,"], "Ry": ["-2.772e-08,"], "Rz": ["0.0003019"], "x_global": ["1855"], "y_global": ["1213"], "z_global": ["9197"], "average_hit_x": ["1813"], "average_hit_y": ["694"], "average_hit_z": ["9193"], "nTracks": ["117423"], "nHits": ["117423"], "localDeltaChi2": [10.62]}, "FT/T3/X1/HL1/Q3/M4": {"Tx": ["-0.9011,"], "Ty": ["-0.000143,"], "Tz": ["-0.5277,"], "Rx": ["-0.0005312,"], "Ry": ["-2.953e-07,"], "Rz": ["0.0001713"], "x_global": ["2385"], "y_global": ["1213"], "z_global": ["9197"], "average_hit_x": ["2349"], "average_hit_y": ["778.5"], "average_hit_z": ["9193"], "nTracks": ["49777"], "nHits": ["49777"], "localDeltaChi2": [43.245]}, "FT/T3/X1/HL1/Q3/M5": {"Tx": ["-1.165,"], "Ty": ["0.0006112,"], "Tz": ["0.67,"], "Rx": ["-9.568e-05,"], "Ry": ["-4.868e-08,"], "Rz": ["0.0001186"], "x_global": ["2915"], "y_global": ["1213"], "z_global": ["9197"], "average_hit_x": ["2746"], "average_hit_y": ["719.8"], "average_hit_z": ["9193"], "nTracks": ["10008"], "nHits": ["10008"], "localDeltaChi2": [826.5]}, "FT/T3/X2/HL0/Q0/M0": {"Tx": ["-0.1238,"], "Ty": ["-0.006682,"], "Tz": ["-2.538,"], "Rx": ["-0.001218,"], "Ry": ["-3.447e-07,"], "Rz": ["-1.617e-05"], "x_global": ["-265"], "y_global": ["-1213"], "z_global": ["9399"], "average_hit_x": ["-247.1"], "average_hit_y": ["-394.4"], "average_hit_z": ["9403"], "nTracks": ["357304"], "nHits": ["357304"], "localDeltaChi2": [1985.5]}, "FT/T3/X2/HL0/Q0/M1": {"Tx": ["0.153,"], "Ty": ["-0.0027,"], "Tz": ["-2.271,"], "Rx": ["-0.0005216,"], "Ry": ["-2.956e-07,"], "Rz": ["0.0003024"], "x_global": ["-795"], "y_global": ["-1213"], "z_global": ["9399"], "average_hit_x": ["-805.9"], "average_hit_y": ["-439.9"], "average_hit_z": ["9402"], "nTracks": ["416279"], "nHits": ["416279"], "localDeltaChi2": [16630.0]}, "FT/T3/X2/HL0/Q0/M2": {"Tx": ["-0.1093,"], "Ty": ["-0.0003289,"], "Tz": ["-2.01,"], "Rx": ["-3.14e-05,"], "Ry": ["-1.766e-07,"], "Rz": ["0.0004427"], "x_global": ["-1325"], "y_global": ["-1213"], "z_global": ["9399"], "average_hit_x": ["-1299"], "average_hit_y": ["-547.5"], "average_hit_z": ["9401"], "nTracks": ["296205"], "nHits": ["296205"], "localDeltaChi2": [9815.0]}, "FT/T3/X2/HL0/Q0/M3": {"Tx": ["0.1026,"], "Ty": ["-0.001914,"], "Tz": ["-1.574,"], "Rx": ["-0.0005404,"], "Ry": ["-3.952e-07,"], "Rz": ["0.0005592"], "x_global": ["-1855"], "y_global": ["-1213"], "z_global": ["9399"], "average_hit_x": ["-1786"], "average_hit_y": ["-716.1"], "average_hit_z": ["9402"], "nTracks": ["100513"], "nHits": ["100513"], "localDeltaChi2": [9130.0]}, "FT/T3/X2/HL0/Q0/M4": {"Tx": ["0.2789,"], "Ty": ["-0.001235,"], "Tz": ["-1.542,"], "Rx": ["-0.0003117,"], "Ry": ["-2.242e-07,"], "Rz": ["0.0005801"], "x_global": ["-2385"], "y_global": ["-1213"], "z_global": ["9399"], "average_hit_x": ["-2383"], "average_hit_y": ["-789.5"], "average_hit_z": ["9402"], "nTracks": ["43179"], "nHits": ["43179"], "localDeltaChi2": [8055.0]}, "FT/T3/X2/HL0/Q0/M5": {"Tx": ["0.2652,"], "Ty": ["-0.0008604,"], "Tz": ["-1.911,"], "Rx": ["-7.691e-05,"], "Ry": ["-3.799e-08,"], "Rz": ["0.0005014"], "x_global": ["-2915"], "y_global": ["-1213"], "z_global": ["9399"], "average_hit_x": ["-2786"], "average_hit_y": ["-738.9"], "average_hit_z": ["9401"], "nTracks": ["14313"], "nHits": ["14313"], "localDeltaChi2": [7975.0]}, "FT/T3/X2/HL0/Q2/M0": {"Tx": ["-0.03624,"], "Ty": ["-0.0009385,"], "Tz": ["-1.187,"], "Rx": ["-0.0001091,"], "Ry": ["-2.516e-07,"], "Rz": ["0.0001481"], "x_global": ["-265"], "y_global": ["1213"], "z_global": ["9407"], "average_hit_x": ["-223.9"], "average_hit_y": ["460.8"], "average_hit_z": ["9402"], "nTracks": ["239794"], "nHits": ["239794"], "localDeltaChi2": [1991.5]}, "FT/T3/X2/HL0/Q2/M1": {"Tx": ["0.1136,"], "Ty": ["0.0007328,"], "Tz": ["-1.406,"], "Rx": ["0.0001922,"], "Ry": ["5.646e-08,"], "Rz": ["-0.0005223"], "x_global": ["-795"], "y_global": ["1213"], "z_global": ["9407"], "average_hit_x": ["-812"], "average_hit_y": ["212.3"], "average_hit_z": ["9401"], "nTracks": ["117893"], "nHits": ["117893"], "localDeltaChi2": [16620.0]}, "FT/T3/X2/HL0/Q2/M2": {"Tx": ["0.09439,"], "Ty": ["-0.001258,"], "Tz": ["-2.336,"], "Rx": ["-0.0002957,"], "Ry": ["-9.461e-08,"], "Rz": ["-0.0004303"], "x_global": ["-1325"], "y_global": ["1213"], "z_global": ["9407"], "average_hit_x": ["-1303"], "average_hit_y": ["211.2"], "average_hit_z": ["9402"], "nTracks": ["94541"], "nHits": ["94541"], "localDeltaChi2": [9810.0]}, "FT/T3/X2/HL0/Q2/M3": {"Tx": ["-1.002,"], "Ty": ["-0.0008249,"], "Tz": ["-0.4323,"], "Rx": ["0.0004034,"], "Ry": ["1.318e-07,"], "Rz": ["0.0001823"], "x_global": ["-1855"], "y_global": ["1213"], "z_global": ["9407"], "average_hit_x": ["-1835"], "average_hit_y": ["282.3"], "average_hit_z": ["9402"], "nTracks": ["43961"], "nHits": ["43961"], "localDeltaChi2": [9130.0]}, "FT/T3/X2/HL0/Q2/M4": {"Tx": ["-0.4892,"], "Ty": ["0.001489,"], "Tz": ["-0.864,"], "Rx": ["0.0002469,"], "Ry": ["2.767e-08,"], "Rz": ["-0.0004067"], "x_global": ["-2385"], "y_global": ["1213"], "z_global": ["9407"], "average_hit_x": ["-2336"], "average_hit_y": ["389.5"], "average_hit_z": ["9402"], "nTracks": ["19467"], "nHits": ["19467"], "localDeltaChi2": [8055.0]}, "FT/T3/X2/HL0/Q2/M5": {"Tx": ["-0.3454,"], "Ty": ["0.002704,"], "Tz": ["-1.222,"], "Rx": ["0.0004909,"], "Ry": ["-5.524e-08,"], "Rz": ["-0.0004353"], "x_global": ["-2915"], "y_global": ["1213"], "z_global": ["9407"], "average_hit_x": ["-2778"], "average_hit_y": ["462.5"], "average_hit_z": ["9401"], "nTracks": ["6343"], "nHits": ["6343"], "localDeltaChi2": [7975.0]}, "FT/T3/X2/HL1/Q1/M0": {"Tx": ["-0.3306,"], "Ty": ["0.0003269,"], "Tz": ["1.27,"], "Rx": ["-0.0001077,"], "Ry": ["-1.523e-07,"], "Rz": ["4.191e-05"], "x_global": ["265"], "y_global": ["-1213"], "z_global": ["9399"], "average_hit_x": ["252.8"], "average_hit_y": ["-417.9"], "average_hit_z": ["9404"], "nTracks": ["411312"], "nHits": ["411312"], "localDeltaChi2": [3749.5]}, "FT/T3/X2/HL1/Q1/M1": {"Tx": ["-0.6046,"], "Ty": ["0.0004339,"], "Tz": ["0.9403,"], "Rx": ["-0.00036,"], "Ry": ["4.693e-07,"], "Rz": ["0.0002752"], "x_global": ["795"], "y_global": ["-1213"], "z_global": ["9399"], "average_hit_x": ["766.7"], "average_hit_y": ["-271.2"], "average_hit_z": ["9404"], "nTracks": ["170478"], "nHits": ["170478"], "localDeltaChi2": [453.15]}, "FT/T3/X2/HL1/Q1/M2": {"Tx": ["-0.9581,"], "Ty": ["0.001621,"], "Tz": ["1.268,"], "Rx": ["-0.0006207,"], "Ry": ["2.389e-07,"], "Rz": ["0.0002462"], "x_global": ["1325"], "y_global": ["-1213"], "z_global": ["9399"], "average_hit_x": ["1305"], "average_hit_y": ["-209.1"], "average_hit_z": ["9405"], "nTracks": ["91796"], "nHits": ["91796"], "localDeltaChi2": [518.0]}, "FT/T3/X2/HL1/Q1/M3": {"Tx": ["-0.8701,"], "Ty": ["-0.0001219,"], "Tz": ["0.933,"], "Rx": ["-0.0001722,"], "Ry": ["5.173e-07,"], "Rz": ["0.0005114"], "x_global": ["1855"], "y_global": ["-1213"], "z_global": ["9399"], "average_hit_x": ["1715"], "average_hit_y": ["-257.4"], "average_hit_z": ["9404"], "nTracks": ["26397"], "nHits": ["26397"], "localDeltaChi2": [154.45]}, "FT/T3/X2/HL1/Q1/M4": {"Tx": ["-0.1864,"], "Ty": ["0.002288,"], "Tz": ["1.079,"], "Rx": ["-0.0004262,"], "Ry": ["4.674e-08,"], "Rz": ["-0.0007563"], "x_global": ["2385"], "y_global": ["-1213"], "z_global": ["9399"], "average_hit_x": ["2580"], "average_hit_y": ["-444.8"], "average_hit_z": ["9404"], "nTracks": ["5446"], "nHits": ["5446"], "localDeltaChi2": [0.42165]}, "FT/T3/X2/HL1/Q1/M5": {"Tx": ["-0.3573,"], "Ty": ["0.002037,"], "Tz": ["0.3279,"], "Rx": ["-0.0005982,"], "Ry": ["1.079e-07,"], "Rz": ["-0.000539"], "x_global": ["2915"], "y_global": ["-1213"], "z_global": ["9399"], "average_hit_x": ["2800"], "average_hit_y": ["-466.4"], "average_hit_z": ["9404"], "nTracks": ["8529"], "nHits": ["8529"], "localDeltaChi2": [750.0]}, "FT/T3/X2/HL1/Q3/M0": {"Tx": ["0.2753,"], "Ty": ["-0.002809,"], "Tz": ["-0.8109,"], "Rx": ["-0.001815,"], "Ry": ["6.992e-07,"], "Rz": ["3.617e-06"], "x_global": ["265"], "y_global": ["1213"], "z_global": ["9407"], "average_hit_x": ["250.4"], "average_hit_y": ["413.8"], "average_hit_z": ["9406"], "nTracks": ["515979"], "nHits": ["515979"], "localDeltaChi2": [3763.5]}, "FT/T3/X2/HL1/Q3/M1": {"Tx": ["-0.1397,"], "Ty": ["-0.001584,"], "Tz": ["-0.5252,"], "Rx": ["-0.001573,"], "Ry": ["3.114e-07,"], "Rz": ["0.0003386"], "x_global": ["795"], "y_global": ["1213"], "z_global": ["9407"], "average_hit_x": ["784.5"], "average_hit_y": ["421.9"], "average_hit_z": ["9405"], "nTracks": ["382953"], "nHits": ["382953"], "localDeltaChi2": [465.45]}, "FT/T3/X2/HL1/Q3/M2": {"Tx": ["0.2299,"], "Ty": ["0.001497,"], "Tz": ["0.3547,"], "Rx": ["-0.001378,"], "Ry": ["5.68e-07,"], "Rz": ["0.0003542"], "x_global": ["1325"], "y_global": ["1213"], "z_global": ["9407"], "average_hit_x": ["1303"], "average_hit_y": ["535.2"], "average_hit_z": ["9405"], "nTracks": ["249741"], "nHits": ["249741"], "localDeltaChi2": [529.0]}, "FT/T3/X2/HL1/Q3/M3": {"Tx": ["-0.1733,"], "Ty": ["-0.001228,"], "Tz": ["-0.5483,"], "Rx": ["-0.001395,"], "Ry": ["6.175e-07,"], "Rz": ["0.0003489"], "x_global": ["1855"], "y_global": ["1213"], "z_global": ["9407"], "average_hit_x": ["1810"], "average_hit_y": ["688.7"], "average_hit_z": ["9405"], "nTracks": ["116213"], "nHits": ["116213"], "localDeltaChi2": [162.8]}, "FT/T3/X2/HL1/Q3/M4": {"Tx": ["0.8176,"], "Ty": ["0.002293,"], "Tz": ["0.7081,"], "Rx": ["-0.0007313,"], "Ry": ["4.17e-07,"], "Rz": ["0.0002359"], "x_global": ["2385"], "y_global": ["1213"], "z_global": ["9407"], "average_hit_x": ["2351"], "average_hit_y": ["788.9"], "average_hit_z": ["9404"], "nTracks": ["53846"], "nHits": ["53846"], "localDeltaChi2": [4.8285]}, "FT/T3/X2/HL1/Q3/M5": {"Tx": ["1.285,"], "Ty": ["0.0002377,"], "Tz": ["1.216,"], "Rx": ["0.0001346,"], "Ry": ["-1.463e-07,"], "Rz": ["-0.0002257"], "x_global": ["2915"], "y_global": ["1213"], "z_global": ["9407"], "average_hit_x": ["2786"], "average_hit_y": ["774.8"], "average_hit_z": ["9404"], "nTracks": ["15075"], "nHits": ["15075"], "localDeltaChi2": [750.5]}}